{"url":"http:\/\/proyect_airbnb.test\/anfitrion\/ActualizarServicio","method":"POST","isAJAX":false,"startTime":1666712707.077205,"totalTime":416.8,"totalMemory":"5.247","segmentDuration":60,"segmentCount":7,"CI_VERSION":"4.1.8","collectors":[{"title":"Timers","titleSafe":"timers","titleDetails":"","display":[],"badgeValue":null,"isEmpty":false,"hasTabContent":false,"hasLabel":false,"icon":"","hasTimelineData":true,"timelineData":[{"name":"Bootstrap","component":"Timer","start":1666712707.143138,"duration":0.05526018142700195},{"name":"Routing","component":"Timer","start":1666712707.198401,"duration":0.005713939666748047},{"name":"Before Filters","component":"Timer","start":1666712707.206735,"duration":0.0458521842956543},{"name":"Controller","component":"Timer","start":1666712707.252593,"duration":0.24137091636657715},{"name":"Controller Constructor","component":"Timer","start":1666712707.252595,"duration":0.012006998062133789},{"name":"After Filters","component":"Timer","start":1666712707.493992,"duration":0.0006189346313476562}]},{"title":"Database","titleSafe":"database","titleDetails":"(23 total Queries, 23 of them unique across 1 Connection)","display":{"queries":[{"hover":"","class":"","duration":"0.43 ms","sql":"<strong>SELECT<\/strong> *\n<strong>FROM<\/strong> `tbl_usuarios`\n<strong>WHERE<\/strong> `idUsuario` = &#039;1&#039;\n <strong>LIMIT<\/strong> 1","trace":[{"file":"SYSTEMPATH\\Database\\BaseBuilder.php:1455","function":"\u00a0\u00a0\u00a0\u00a0\u00a0\u00a0\u00a0\u00a0CodeIgniter\\Database\\BaseConnection->query()","index":"\u00a0\u00a01\u00a0\u00a0\u00a0\u00a0"},{"file":"SYSTEMPATH\\Model.php:210","function":"\u00a0\u00a0\u00a0\u00a0\u00a0\u00a0\u00a0\u00a0CodeIgniter\\Database\\BaseBuilder->get()","index":"\u00a0\u00a02\u00a0\u00a0\u00a0\u00a0"},{"file":"SYSTEMPATH\\BaseModel.php:622","function":"\u00a0\u00a0\u00a0\u00a0\u00a0\u00a0\u00a0\u00a0CodeIgniter\\Model->doFirst()","index":"\u00a0\u00a03\u00a0\u00a0\u00a0\u00a0"},{"file":"APPPATH\\Models\\UsuarioModel.php:69","function":"\u00a0\u00a0\u00a0\u00a0\u00a0\u00a0\u00a0\u00a0CodeIgniter\\BaseModel->first()","index":"\u00a0\u00a04\u00a0\u00a0\u00a0\u00a0"},{"file":"APPPATH\\Filters\\Roles.php:26","function":"\u00a0\u00a0\u00a0\u00a0\u00a0\u00a0\u00a0\u00a0App\\Models\\UsuarioModel->buscarUsuario()","index":"\u00a0\u00a05\u00a0\u00a0\u00a0\u00a0"},{"file":"SYSTEMPATH\\Filters\\Filters.php:173","function":"\u00a0\u00a0\u00a0\u00a0\u00a0\u00a0\u00a0\u00a0App\\Filters\\Roles->before()","index":"\u00a0\u00a06\u00a0\u00a0\u00a0\u00a0"},{"file":"SYSTEMPATH\\CodeIgniter.php:386","function":"\u00a0\u00a0\u00a0\u00a0\u00a0\u00a0\u00a0\u00a0CodeIgniter\\Filters\\Filters->run()","index":"\u00a0\u00a07\u00a0\u00a0\u00a0\u00a0"},{"file":"SYSTEMPATH\\CodeIgniter.php:320","function":"\u00a0\u00a0\u00a0\u00a0\u00a0\u00a0\u00a0\u00a0CodeIgniter\\CodeIgniter->handleRequest()","index":"\u00a0\u00a08\u00a0\u00a0\u00a0\u00a0"},{"file":"FCPATH\\index.php:37","function":"\u00a0\u00a0\u00a0\u00a0\u00a0\u00a0\u00a0\u00a0CodeIgniter\\CodeIgniter->run()","index":"\u00a0\u00a09\u00a0\u00a0\u00a0\u00a0"}],"trace-file":"APPPATH\\Models\\UsuarioModel.php:69","qid":"1f37384973d2755a6f6584c687443393"},{"hover":"","class":"","duration":"0.72 ms","sql":"<strong>SELECT<\/strong> *\n<strong>FROM<\/strong> `tbl_roles`\n<strong>WHERE<\/strong> `idRol` = &#039;3&#039;","trace":[{"file":"SYSTEMPATH\\Database\\BaseBuilder.php:1455","function":"\u00a0\u00a0\u00a0\u00a0\u00a0\u00a0\u00a0\u00a0CodeIgniter\\Database\\BaseConnection->query()","index":"\u00a0\u00a01\u00a0\u00a0\u00a0\u00a0"},{"file":"APPPATH\\Models\\UsuarioModel.php:73","function":"\u00a0\u00a0\u00a0\u00a0\u00a0\u00a0\u00a0\u00a0CodeIgniter\\Database\\BaseBuilder->get()","index":"\u00a0\u00a02\u00a0\u00a0\u00a0\u00a0"},{"file":"APPPATH\\Filters\\Roles.php:37","function":"\u00a0\u00a0\u00a0\u00a0\u00a0\u00a0\u00a0\u00a0App\\Models\\UsuarioModel->buscarRol()","index":"\u00a0\u00a03\u00a0\u00a0\u00a0\u00a0"},{"file":"SYSTEMPATH\\Filters\\Filters.php:173","function":"\u00a0\u00a0\u00a0\u00a0\u00a0\u00a0\u00a0\u00a0App\\Filters\\Roles->before()","index":"\u00a0\u00a04\u00a0\u00a0\u00a0\u00a0"},{"file":"SYSTEMPATH\\CodeIgniter.php:386","function":"\u00a0\u00a0\u00a0\u00a0\u00a0\u00a0\u00a0\u00a0CodeIgniter\\Filters\\Filters->run()","index":"\u00a0\u00a05\u00a0\u00a0\u00a0\u00a0"},{"file":"SYSTEMPATH\\CodeIgniter.php:320","function":"\u00a0\u00a0\u00a0\u00a0\u00a0\u00a0\u00a0\u00a0CodeIgniter\\CodeIgniter->handleRequest()","index":"\u00a0\u00a06\u00a0\u00a0\u00a0\u00a0"},{"file":"FCPATH\\index.php:37","function":"\u00a0\u00a0\u00a0\u00a0\u00a0\u00a0\u00a0\u00a0CodeIgniter\\CodeIgniter->run()","index":"\u00a0\u00a07\u00a0\u00a0\u00a0\u00a0"}],"trace-file":"APPPATH\\Models\\UsuarioModel.php:73","qid":"43084d43c118a3c420cbf06bd6c9f20d"},{"hover":"","class":"","duration":"3.27 ms","sql":"<strong>SELECT<\/strong> *\n<strong>FROM<\/strong> `tbl_servicios`","trace":[{"file":"SYSTEMPATH\\Database\\BaseBuilder.php:1455","function":"\u00a0\u00a0\u00a0\u00a0\u00a0\u00a0\u00a0\u00a0CodeIgniter\\Database\\BaseConnection->query()","index":"\u00a0\u00a01\u00a0\u00a0\u00a0\u00a0"},{"file":"SYSTEMPATH\\Model.php:183","function":"\u00a0\u00a0\u00a0\u00a0\u00a0\u00a0\u00a0\u00a0CodeIgniter\\Database\\BaseBuilder->get()","index":"\u00a0\u00a02\u00a0\u00a0\u00a0\u00a0"},{"file":"SYSTEMPATH\\BaseModel.php:584","function":"\u00a0\u00a0\u00a0\u00a0\u00a0\u00a0\u00a0\u00a0CodeIgniter\\Model->doFindAll()","index":"\u00a0\u00a03\u00a0\u00a0\u00a0\u00a0"},{"file":"APPPATH\\Controllers\\Anfitrion\\UpdateDelete.php:68","function":"\u00a0\u00a0\u00a0\u00a0\u00a0\u00a0\u00a0\u00a0CodeIgniter\\BaseModel->findAll()","index":"\u00a0\u00a04\u00a0\u00a0\u00a0\u00a0"},{"file":"SYSTEMPATH\\CodeIgniter.php:825","function":"\u00a0\u00a0\u00a0\u00a0\u00a0\u00a0\u00a0\u00a0App\\Controllers\\Anfitrion\\UpdateDelete->ActualizarServicio()","index":"\u00a0\u00a05\u00a0\u00a0\u00a0\u00a0"},{"file":"SYSTEMPATH\\CodeIgniter.php:412","function":"\u00a0\u00a0\u00a0\u00a0\u00a0\u00a0\u00a0\u00a0CodeIgniter\\CodeIgniter->runController()","index":"\u00a0\u00a06\u00a0\u00a0\u00a0\u00a0"},{"file":"SYSTEMPATH\\CodeIgniter.php:320","function":"\u00a0\u00a0\u00a0\u00a0\u00a0\u00a0\u00a0\u00a0CodeIgniter\\CodeIgniter->handleRequest()","index":"\u00a0\u00a07\u00a0\u00a0\u00a0\u00a0"},{"file":"FCPATH\\index.php:37","function":"\u00a0\u00a0\u00a0\u00a0\u00a0\u00a0\u00a0\u00a0CodeIgniter\\CodeIgniter->run()","index":"\u00a0\u00a08\u00a0\u00a0\u00a0\u00a0"}],"trace-file":"APPPATH\\Controllers\\Anfitrion\\UpdateDelete.php:68","qid":"132d38afaf296fd8f762f51b590f58f8"},{"hover":"","class":"","duration":"1.88 ms","sql":"<strong>SELECT<\/strong> 1\n<strong>FROM<\/strong> `tbl_tipo_hospedajes`\n<strong>WHERE<\/strong> `idTipoHospedaje` = &#039;1&#039;\n <strong>LIMIT<\/strong> 1","trace":[{"file":"SYSTEMPATH\\Database\\BaseBuilder.php:1455","function":"\u00a0\u00a0\u00a0\u00a0\u00a0\u00a0\u00a0\u00a0CodeIgniter\\Database\\BaseConnection->query()","index":"\u00a0\u00a01\u00a0\u00a0\u00a0\u00a0"},{"file":"SYSTEMPATH\\Validation\\Rules.php:104","function":"\u00a0\u00a0\u00a0\u00a0\u00a0\u00a0\u00a0\u00a0CodeIgniter\\Database\\BaseBuilder->get()","index":"\u00a0\u00a02\u00a0\u00a0\u00a0\u00a0"},{"file":"SYSTEMPATH\\Validation\\Validation.php:292","function":"\u00a0\u00a0\u00a0\u00a0\u00a0\u00a0\u00a0\u00a0CodeIgniter\\Validation\\Rules->is_not_unique()","index":"\u00a0\u00a03\u00a0\u00a0\u00a0\u00a0"},{"file":"SYSTEMPATH\\Validation\\Validation.php:157","function":"\u00a0\u00a0\u00a0\u00a0\u00a0\u00a0\u00a0\u00a0CodeIgniter\\Validation\\Validation->processRules()","index":"\u00a0\u00a04\u00a0\u00a0\u00a0\u00a0"},{"file":"APPPATH\\Controllers\\Anfitrion\\UpdateDelete.php:149","function":"\u00a0\u00a0\u00a0\u00a0\u00a0\u00a0\u00a0\u00a0CodeIgniter\\Validation\\Validation->run()","index":"\u00a0\u00a05\u00a0\u00a0\u00a0\u00a0"},{"file":"SYSTEMPATH\\CodeIgniter.php:825","function":"\u00a0\u00a0\u00a0\u00a0\u00a0\u00a0\u00a0\u00a0App\\Controllers\\Anfitrion\\UpdateDelete->ActualizarServicio()","index":"\u00a0\u00a06\u00a0\u00a0\u00a0\u00a0"},{"file":"SYSTEMPATH\\CodeIgniter.php:412","function":"\u00a0\u00a0\u00a0\u00a0\u00a0\u00a0\u00a0\u00a0CodeIgniter\\CodeIgniter->runController()","index":"\u00a0\u00a07\u00a0\u00a0\u00a0\u00a0"},{"file":"SYSTEMPATH\\CodeIgniter.php:320","function":"\u00a0\u00a0\u00a0\u00a0\u00a0\u00a0\u00a0\u00a0CodeIgniter\\CodeIgniter->handleRequest()","index":"\u00a0\u00a08\u00a0\u00a0\u00a0\u00a0"},{"file":"FCPATH\\index.php:37","function":"\u00a0\u00a0\u00a0\u00a0\u00a0\u00a0\u00a0\u00a0CodeIgniter\\CodeIgniter->run()","index":"\u00a0\u00a09\u00a0\u00a0\u00a0\u00a0"}],"trace-file":"APPPATH\\Controllers\\Anfitrion\\UpdateDelete.php:149","qid":"6ee37338d9469ba0e0b7df94e3d5790f"},{"hover":"","class":"","duration":"3.03 ms","sql":"<strong>SELECT<\/strong> `idSubServicio`\n<strong>FROM<\/strong> `tbl_sub_servicios`","trace":[{"file":"SYSTEMPATH\\Database\\BaseBuilder.php:1455","function":"\u00a0\u00a0\u00a0\u00a0\u00a0\u00a0\u00a0\u00a0CodeIgniter\\Database\\BaseConnection->query()","index":"\u00a0\u00a01\u00a0\u00a0\u00a0\u00a0"},{"file":"SYSTEMPATH\\Model.php:145","function":"\u00a0\u00a0\u00a0\u00a0\u00a0\u00a0\u00a0\u00a0CodeIgniter\\Database\\BaseBuilder->get()","index":"\u00a0\u00a02\u00a0\u00a0\u00a0\u00a0"},{"file":"SYSTEMPATH\\BaseModel.php:523","function":"\u00a0\u00a0\u00a0\u00a0\u00a0\u00a0\u00a0\u00a0CodeIgniter\\Model->doFind()","index":"\u00a0\u00a03\u00a0\u00a0\u00a0\u00a0"},{"file":"SYSTEMPATH\\Model.php:161","function":"\u00a0\u00a0\u00a0\u00a0\u00a0\u00a0\u00a0\u00a0CodeIgniter\\BaseModel->find()","index":"\u00a0\u00a04\u00a0\u00a0\u00a0\u00a0"},{"file":"SYSTEMPATH\\BaseModel.php:554","function":"\u00a0\u00a0\u00a0\u00a0\u00a0\u00a0\u00a0\u00a0CodeIgniter\\Model->doFindColumn()","index":"\u00a0\u00a05\u00a0\u00a0\u00a0\u00a0"},{"file":"APPPATH\\Controllers\\Anfitrion\\UpdateDelete.php:194","function":"\u00a0\u00a0\u00a0\u00a0\u00a0\u00a0\u00a0\u00a0CodeIgniter\\BaseModel->findColumn()","index":"\u00a0\u00a06\u00a0\u00a0\u00a0\u00a0"},{"file":"SYSTEMPATH\\CodeIgniter.php:825","function":"\u00a0\u00a0\u00a0\u00a0\u00a0\u00a0\u00a0\u00a0App\\Controllers\\Anfitrion\\UpdateDelete->ActualizarServicio()","index":"\u00a0\u00a07\u00a0\u00a0\u00a0\u00a0"},{"file":"SYSTEMPATH\\CodeIgniter.php:412","function":"\u00a0\u00a0\u00a0\u00a0\u00a0\u00a0\u00a0\u00a0CodeIgniter\\CodeIgniter->runController()","index":"\u00a0\u00a08\u00a0\u00a0\u00a0\u00a0"},{"file":"SYSTEMPATH\\CodeIgniter.php:320","function":"\u00a0\u00a0\u00a0\u00a0\u00a0\u00a0\u00a0\u00a0CodeIgniter\\CodeIgniter->handleRequest()","index":"\u00a0\u00a09\u00a0\u00a0\u00a0\u00a0"},{"file":"FCPATH\\index.php:37","function":"\u00a0\u00a0\u00a0\u00a0\u00a0\u00a0\u00a0\u00a0CodeIgniter\\CodeIgniter->run()","index":"\u00a010\u00a0\u00a0\u00a0\u00a0"}],"trace-file":"APPPATH\\Controllers\\Anfitrion\\UpdateDelete.php:194","qid":"2c416de5c7266d07411266456e0b0f53"},{"hover":"","class":"","duration":"2.17 ms","sql":"<strong>SELECT<\/strong> `idSaludSeguridad`\n<strong>FROM<\/strong> `tbl_salud_y_seguridad`","trace":[{"file":"SYSTEMPATH\\Database\\BaseBuilder.php:1455","function":"\u00a0\u00a0\u00a0\u00a0\u00a0\u00a0\u00a0\u00a0CodeIgniter\\Database\\BaseConnection->query()","index":"\u00a0\u00a01\u00a0\u00a0\u00a0\u00a0"},{"file":"SYSTEMPATH\\Model.php:145","function":"\u00a0\u00a0\u00a0\u00a0\u00a0\u00a0\u00a0\u00a0CodeIgniter\\Database\\BaseBuilder->get()","index":"\u00a0\u00a02\u00a0\u00a0\u00a0\u00a0"},{"file":"SYSTEMPATH\\BaseModel.php:523","function":"\u00a0\u00a0\u00a0\u00a0\u00a0\u00a0\u00a0\u00a0CodeIgniter\\Model->doFind()","index":"\u00a0\u00a03\u00a0\u00a0\u00a0\u00a0"},{"file":"SYSTEMPATH\\Model.php:161","function":"\u00a0\u00a0\u00a0\u00a0\u00a0\u00a0\u00a0\u00a0CodeIgniter\\BaseModel->find()","index":"\u00a0\u00a04\u00a0\u00a0\u00a0\u00a0"},{"file":"SYSTEMPATH\\BaseModel.php:554","function":"\u00a0\u00a0\u00a0\u00a0\u00a0\u00a0\u00a0\u00a0CodeIgniter\\Model->doFindColumn()","index":"\u00a0\u00a05\u00a0\u00a0\u00a0\u00a0"},{"file":"APPPATH\\Controllers\\Anfitrion\\UpdateDelete.php:203","function":"\u00a0\u00a0\u00a0\u00a0\u00a0\u00a0\u00a0\u00a0CodeIgniter\\BaseModel->findColumn()","index":"\u00a0\u00a06\u00a0\u00a0\u00a0\u00a0"},{"file":"SYSTEMPATH\\CodeIgniter.php:825","function":"\u00a0\u00a0\u00a0\u00a0\u00a0\u00a0\u00a0\u00a0App\\Controllers\\Anfitrion\\UpdateDelete->ActualizarServicio()","index":"\u00a0\u00a07\u00a0\u00a0\u00a0\u00a0"},{"file":"SYSTEMPATH\\CodeIgniter.php:412","function":"\u00a0\u00a0\u00a0\u00a0\u00a0\u00a0\u00a0\u00a0CodeIgniter\\CodeIgniter->runController()","index":"\u00a0\u00a08\u00a0\u00a0\u00a0\u00a0"},{"file":"SYSTEMPATH\\CodeIgniter.php:320","function":"\u00a0\u00a0\u00a0\u00a0\u00a0\u00a0\u00a0\u00a0CodeIgniter\\CodeIgniter->handleRequest()","index":"\u00a0\u00a09\u00a0\u00a0\u00a0\u00a0"},{"file":"FCPATH\\index.php:37","function":"\u00a0\u00a0\u00a0\u00a0\u00a0\u00a0\u00a0\u00a0CodeIgniter\\CodeIgniter->run()","index":"\u00a010\u00a0\u00a0\u00a0\u00a0"}],"trace-file":"APPPATH\\Controllers\\Anfitrion\\UpdateDelete.php:203","qid":"5b2883c57319051149bdc23005b677c0"},{"hover":"","class":"","duration":"1.96 ms","sql":"<strong>SELECT<\/strong> `idReglaServicio`\n<strong>FROM<\/strong> `tbl_reglas_servicios`","trace":[{"file":"SYSTEMPATH\\Database\\BaseBuilder.php:1455","function":"\u00a0\u00a0\u00a0\u00a0\u00a0\u00a0\u00a0\u00a0CodeIgniter\\Database\\BaseConnection->query()","index":"\u00a0\u00a01\u00a0\u00a0\u00a0\u00a0"},{"file":"SYSTEMPATH\\Model.php:145","function":"\u00a0\u00a0\u00a0\u00a0\u00a0\u00a0\u00a0\u00a0CodeIgniter\\Database\\BaseBuilder->get()","index":"\u00a0\u00a02\u00a0\u00a0\u00a0\u00a0"},{"file":"SYSTEMPATH\\BaseModel.php:523","function":"\u00a0\u00a0\u00a0\u00a0\u00a0\u00a0\u00a0\u00a0CodeIgniter\\Model->doFind()","index":"\u00a0\u00a03\u00a0\u00a0\u00a0\u00a0"},{"file":"SYSTEMPATH\\Model.php:161","function":"\u00a0\u00a0\u00a0\u00a0\u00a0\u00a0\u00a0\u00a0CodeIgniter\\BaseModel->find()","index":"\u00a0\u00a04\u00a0\u00a0\u00a0\u00a0"},{"file":"SYSTEMPATH\\BaseModel.php:554","function":"\u00a0\u00a0\u00a0\u00a0\u00a0\u00a0\u00a0\u00a0CodeIgniter\\Model->doFindColumn()","index":"\u00a0\u00a05\u00a0\u00a0\u00a0\u00a0"},{"file":"APPPATH\\Controllers\\Anfitrion\\UpdateDelete.php:212","function":"\u00a0\u00a0\u00a0\u00a0\u00a0\u00a0\u00a0\u00a0CodeIgniter\\BaseModel->findColumn()","index":"\u00a0\u00a06\u00a0\u00a0\u00a0\u00a0"},{"file":"SYSTEMPATH\\CodeIgniter.php:825","function":"\u00a0\u00a0\u00a0\u00a0\u00a0\u00a0\u00a0\u00a0App\\Controllers\\Anfitrion\\UpdateDelete->ActualizarServicio()","index":"\u00a0\u00a07\u00a0\u00a0\u00a0\u00a0"},{"file":"SYSTEMPATH\\CodeIgniter.php:412","function":"\u00a0\u00a0\u00a0\u00a0\u00a0\u00a0\u00a0\u00a0CodeIgniter\\CodeIgniter->runController()","index":"\u00a0\u00a08\u00a0\u00a0\u00a0\u00a0"},{"file":"SYSTEMPATH\\CodeIgniter.php:320","function":"\u00a0\u00a0\u00a0\u00a0\u00a0\u00a0\u00a0\u00a0CodeIgniter\\CodeIgniter->handleRequest()","index":"\u00a0\u00a09\u00a0\u00a0\u00a0\u00a0"},{"file":"FCPATH\\index.php:37","function":"\u00a0\u00a0\u00a0\u00a0\u00a0\u00a0\u00a0\u00a0CodeIgniter\\CodeIgniter->run()","index":"\u00a010\u00a0\u00a0\u00a0\u00a0"}],"trace-file":"APPPATH\\Controllers\\Anfitrion\\UpdateDelete.php:212","qid":"a55b6eb108d0af4772e9e2aa414f0b26"},{"hover":"","class":"","duration":"2.43 ms","sql":"<strong>SELECT<\/strong> `idPoliticaCancelacion`\n<strong>FROM<\/strong> `tbl_politicas_de_cancelacion`","trace":[{"file":"SYSTEMPATH\\Database\\BaseBuilder.php:1455","function":"\u00a0\u00a0\u00a0\u00a0\u00a0\u00a0\u00a0\u00a0CodeIgniter\\Database\\BaseConnection->query()","index":"\u00a0\u00a01\u00a0\u00a0\u00a0\u00a0"},{"file":"SYSTEMPATH\\Model.php:145","function":"\u00a0\u00a0\u00a0\u00a0\u00a0\u00a0\u00a0\u00a0CodeIgniter\\Database\\BaseBuilder->get()","index":"\u00a0\u00a02\u00a0\u00a0\u00a0\u00a0"},{"file":"SYSTEMPATH\\BaseModel.php:523","function":"\u00a0\u00a0\u00a0\u00a0\u00a0\u00a0\u00a0\u00a0CodeIgniter\\Model->doFind()","index":"\u00a0\u00a03\u00a0\u00a0\u00a0\u00a0"},{"file":"SYSTEMPATH\\Model.php:161","function":"\u00a0\u00a0\u00a0\u00a0\u00a0\u00a0\u00a0\u00a0CodeIgniter\\BaseModel->find()","index":"\u00a0\u00a04\u00a0\u00a0\u00a0\u00a0"},{"file":"SYSTEMPATH\\BaseModel.php:554","function":"\u00a0\u00a0\u00a0\u00a0\u00a0\u00a0\u00a0\u00a0CodeIgniter\\Model->doFindColumn()","index":"\u00a0\u00a05\u00a0\u00a0\u00a0\u00a0"},{"file":"APPPATH\\Controllers\\Anfitrion\\UpdateDelete.php:221","function":"\u00a0\u00a0\u00a0\u00a0\u00a0\u00a0\u00a0\u00a0CodeIgniter\\BaseModel->findColumn()","index":"\u00a0\u00a06\u00a0\u00a0\u00a0\u00a0"},{"file":"SYSTEMPATH\\CodeIgniter.php:825","function":"\u00a0\u00a0\u00a0\u00a0\u00a0\u00a0\u00a0\u00a0App\\Controllers\\Anfitrion\\UpdateDelete->ActualizarServicio()","index":"\u00a0\u00a07\u00a0\u00a0\u00a0\u00a0"},{"file":"SYSTEMPATH\\CodeIgniter.php:412","function":"\u00a0\u00a0\u00a0\u00a0\u00a0\u00a0\u00a0\u00a0CodeIgniter\\CodeIgniter->runController()","index":"\u00a0\u00a08\u00a0\u00a0\u00a0\u00a0"},{"file":"SYSTEMPATH\\CodeIgniter.php:320","function":"\u00a0\u00a0\u00a0\u00a0\u00a0\u00a0\u00a0\u00a0CodeIgniter\\CodeIgniter->handleRequest()","index":"\u00a0\u00a09\u00a0\u00a0\u00a0\u00a0"},{"file":"FCPATH\\index.php:37","function":"\u00a0\u00a0\u00a0\u00a0\u00a0\u00a0\u00a0\u00a0CodeIgniter\\CodeIgniter->run()","index":"\u00a010\u00a0\u00a0\u00a0\u00a0"}],"trace-file":"APPPATH\\Controllers\\Anfitrion\\UpdateDelete.php:221","qid":"33ee130a3287290bde46390eee56ace3"},{"hover":"","class":"","duration":"0.32 ms","sql":"<strong>SELECT<\/strong> `idTarifa`\n<strong>FROM<\/strong> `tbl_servicios`\n<strong>WHERE<\/strong> `idServicio` = &#039;2&#039;","trace":[{"file":"SYSTEMPATH\\Database\\BaseBuilder.php:1455","function":"\u00a0\u00a0\u00a0\u00a0\u00a0\u00a0\u00a0\u00a0CodeIgniter\\Database\\BaseConnection->query()","index":"\u00a0\u00a01\u00a0\u00a0\u00a0\u00a0"},{"file":"SYSTEMPATH\\Model.php:145","function":"\u00a0\u00a0\u00a0\u00a0\u00a0\u00a0\u00a0\u00a0CodeIgniter\\Database\\BaseBuilder->get()","index":"\u00a0\u00a02\u00a0\u00a0\u00a0\u00a0"},{"file":"SYSTEMPATH\\BaseModel.php:523","function":"\u00a0\u00a0\u00a0\u00a0\u00a0\u00a0\u00a0\u00a0CodeIgniter\\Model->doFind()","index":"\u00a0\u00a03\u00a0\u00a0\u00a0\u00a0"},{"file":"SYSTEMPATH\\Model.php:161","function":"\u00a0\u00a0\u00a0\u00a0\u00a0\u00a0\u00a0\u00a0CodeIgniter\\BaseModel->find()","index":"\u00a0\u00a04\u00a0\u00a0\u00a0\u00a0"},{"file":"SYSTEMPATH\\BaseModel.php:554","function":"\u00a0\u00a0\u00a0\u00a0\u00a0\u00a0\u00a0\u00a0CodeIgniter\\Model->doFindColumn()","index":"\u00a0\u00a05\u00a0\u00a0\u00a0\u00a0"},{"file":"APPPATH\\Controllers\\Anfitrion\\UpdateDelete.php:239","function":"\u00a0\u00a0\u00a0\u00a0\u00a0\u00a0\u00a0\u00a0CodeIgniter\\BaseModel->findColumn()","index":"\u00a0\u00a06\u00a0\u00a0\u00a0\u00a0"},{"file":"SYSTEMPATH\\CodeIgniter.php:825","function":"\u00a0\u00a0\u00a0\u00a0\u00a0\u00a0\u00a0\u00a0App\\Controllers\\Anfitrion\\UpdateDelete->ActualizarServicio()","index":"\u00a0\u00a07\u00a0\u00a0\u00a0\u00a0"},{"file":"SYSTEMPATH\\CodeIgniter.php:412","function":"\u00a0\u00a0\u00a0\u00a0\u00a0\u00a0\u00a0\u00a0CodeIgniter\\CodeIgniter->runController()","index":"\u00a0\u00a08\u00a0\u00a0\u00a0\u00a0"},{"file":"SYSTEMPATH\\CodeIgniter.php:320","function":"\u00a0\u00a0\u00a0\u00a0\u00a0\u00a0\u00a0\u00a0CodeIgniter\\CodeIgniter->handleRequest()","index":"\u00a0\u00a09\u00a0\u00a0\u00a0\u00a0"},{"file":"FCPATH\\index.php:37","function":"\u00a0\u00a0\u00a0\u00a0\u00a0\u00a0\u00a0\u00a0CodeIgniter\\CodeIgniter->run()","index":"\u00a010\u00a0\u00a0\u00a0\u00a0"}],"trace-file":"APPPATH\\Controllers\\Anfitrion\\UpdateDelete.php:239","qid":"1852b13f1732f401e6fb3cb849b85404"},{"hover":"","class":"","duration":"3.01 ms","sql":"<strong>UPDATE<\/strong> `tbl_tarifas` SET `precio` = &#039;100&#039;, `descuento` = &#039;10&#039;, `date_update` = &#039;2022-10-25 09:45:07&#039;\n<strong>WHERE<\/strong> `tbl_tarifas`.`idTarifa` <strong>IN<\/strong> (&#039;2&#039;)","trace":[{"file":"SYSTEMPATH\\Database\\BaseBuilder.php:1913","function":"\u00a0\u00a0\u00a0\u00a0\u00a0\u00a0\u00a0\u00a0CodeIgniter\\Database\\BaseConnection->query()","index":"\u00a0\u00a01\u00a0\u00a0\u00a0\u00a0"},{"file":"SYSTEMPATH\\Model.php:298","function":"\u00a0\u00a0\u00a0\u00a0\u00a0\u00a0\u00a0\u00a0CodeIgniter\\Database\\BaseBuilder->update()","index":"\u00a0\u00a02\u00a0\u00a0\u00a0\u00a0"},{"file":"SYSTEMPATH\\BaseModel.php:865","function":"\u00a0\u00a0\u00a0\u00a0\u00a0\u00a0\u00a0\u00a0CodeIgniter\\Model->doUpdate()","index":"\u00a0\u00a03\u00a0\u00a0\u00a0\u00a0"},{"file":"SYSTEMPATH\\Model.php:651","function":"\u00a0\u00a0\u00a0\u00a0\u00a0\u00a0\u00a0\u00a0CodeIgniter\\BaseModel->update()","index":"\u00a0\u00a04\u00a0\u00a0\u00a0\u00a0"},{"file":"SYSTEMPATH\\BaseModel.php:656","function":"\u00a0\u00a0\u00a0\u00a0\u00a0\u00a0\u00a0\u00a0CodeIgniter\\Model->update()","index":"\u00a0\u00a05\u00a0\u00a0\u00a0\u00a0"},{"file":"APPPATH\\Controllers\\Anfitrion\\UpdateDelete.php:247","function":"\u00a0\u00a0\u00a0\u00a0\u00a0\u00a0\u00a0\u00a0CodeIgniter\\BaseModel->save()","index":"\u00a0\u00a06\u00a0\u00a0\u00a0\u00a0"},{"file":"SYSTEMPATH\\CodeIgniter.php:825","function":"\u00a0\u00a0\u00a0\u00a0\u00a0\u00a0\u00a0\u00a0App\\Controllers\\Anfitrion\\UpdateDelete->ActualizarServicio()","index":"\u00a0\u00a07\u00a0\u00a0\u00a0\u00a0"},{"file":"SYSTEMPATH\\CodeIgniter.php:412","function":"\u00a0\u00a0\u00a0\u00a0\u00a0\u00a0\u00a0\u00a0CodeIgniter\\CodeIgniter->runController()","index":"\u00a0\u00a08\u00a0\u00a0\u00a0\u00a0"},{"file":"SYSTEMPATH\\CodeIgniter.php:320","function":"\u00a0\u00a0\u00a0\u00a0\u00a0\u00a0\u00a0\u00a0CodeIgniter\\CodeIgniter->handleRequest()","index":"\u00a0\u00a09\u00a0\u00a0\u00a0\u00a0"},{"file":"FCPATH\\index.php:37","function":"\u00a0\u00a0\u00a0\u00a0\u00a0\u00a0\u00a0\u00a0CodeIgniter\\CodeIgniter->run()","index":"\u00a010\u00a0\u00a0\u00a0\u00a0"}],"trace-file":"APPPATH\\Controllers\\Anfitrion\\UpdateDelete.php:247","qid":"f4d39b42f572a9d8571d32b5d14f0a71"},{"hover":"","class":"","duration":"1.26 ms","sql":"<strong>UPDATE<\/strong> `tbl_servicios` SET `nombre` = &#039;Servicio 1&#039;, `descripcion` = &#039;Caba\u00f1a con un clima fresco con temperaturas bajas no encontrada en el pais.&#039;, `idTipoHospedaje` = &#039;1&#039;, `direccion` = &#039;Av. 3 calle poniente&#039;, `disponibilidad` = 0, `date_update` = &#039;2022-10-25 09:45:07&#039;\n<strong>WHERE<\/strong> `tbl_servicios`.`idServicio` <strong>IN<\/strong> (&#039;2&#039;)","trace":[{"file":"SYSTEMPATH\\Database\\BaseBuilder.php:1913","function":"\u00a0\u00a0\u00a0\u00a0\u00a0\u00a0\u00a0\u00a0CodeIgniter\\Database\\BaseConnection->query()","index":"\u00a0\u00a01\u00a0\u00a0\u00a0\u00a0"},{"file":"SYSTEMPATH\\Model.php:298","function":"\u00a0\u00a0\u00a0\u00a0\u00a0\u00a0\u00a0\u00a0CodeIgniter\\Database\\BaseBuilder->update()","index":"\u00a0\u00a02\u00a0\u00a0\u00a0\u00a0"},{"file":"SYSTEMPATH\\BaseModel.php:865","function":"\u00a0\u00a0\u00a0\u00a0\u00a0\u00a0\u00a0\u00a0CodeIgniter\\Model->doUpdate()","index":"\u00a0\u00a03\u00a0\u00a0\u00a0\u00a0"},{"file":"SYSTEMPATH\\Model.php:651","function":"\u00a0\u00a0\u00a0\u00a0\u00a0\u00a0\u00a0\u00a0CodeIgniter\\BaseModel->update()","index":"\u00a0\u00a04\u00a0\u00a0\u00a0\u00a0"},{"file":"SYSTEMPATH\\BaseModel.php:656","function":"\u00a0\u00a0\u00a0\u00a0\u00a0\u00a0\u00a0\u00a0CodeIgniter\\Model->update()","index":"\u00a0\u00a05\u00a0\u00a0\u00a0\u00a0"},{"file":"APPPATH\\Controllers\\Anfitrion\\UpdateDelete.php:262","function":"\u00a0\u00a0\u00a0\u00a0\u00a0\u00a0\u00a0\u00a0CodeIgniter\\BaseModel->save()","index":"\u00a0\u00a06\u00a0\u00a0\u00a0\u00a0"},{"file":"SYSTEMPATH\\CodeIgniter.php:825","function":"\u00a0\u00a0\u00a0\u00a0\u00a0\u00a0\u00a0\u00a0App\\Controllers\\Anfitrion\\UpdateDelete->ActualizarServicio()","index":"\u00a0\u00a07\u00a0\u00a0\u00a0\u00a0"},{"file":"SYSTEMPATH\\CodeIgniter.php:412","function":"\u00a0\u00a0\u00a0\u00a0\u00a0\u00a0\u00a0\u00a0CodeIgniter\\CodeIgniter->runController()","index":"\u00a0\u00a08\u00a0\u00a0\u00a0\u00a0"},{"file":"SYSTEMPATH\\CodeIgniter.php:320","function":"\u00a0\u00a0\u00a0\u00a0\u00a0\u00a0\u00a0\u00a0CodeIgniter\\CodeIgniter->handleRequest()","index":"\u00a0\u00a09\u00a0\u00a0\u00a0\u00a0"},{"file":"FCPATH\\index.php:37","function":"\u00a0\u00a0\u00a0\u00a0\u00a0\u00a0\u00a0\u00a0CodeIgniter\\CodeIgniter->run()","index":"\u00a010\u00a0\u00a0\u00a0\u00a0"}],"trace-file":"APPPATH\\Controllers\\Anfitrion\\UpdateDelete.php:262","qid":"86712f09dde23baa352b9bfcfa50da33"},{"hover":"","class":"","duration":"3.45 ms","sql":"<strong>SELECT<\/strong> *\n<strong>FROM<\/strong> `tbl_guardar_sub_servicios`\n<strong>WHERE<\/strong> `idServicio` = &#039;2&#039;","trace":[{"file":"SYSTEMPATH\\Database\\BaseBuilder.php:1455","function":"\u00a0\u00a0\u00a0\u00a0\u00a0\u00a0\u00a0\u00a0CodeIgniter\\Database\\BaseConnection->query()","index":"\u00a0\u00a01\u00a0\u00a0\u00a0\u00a0"},{"file":"SYSTEMPATH\\Model.php:183","function":"\u00a0\u00a0\u00a0\u00a0\u00a0\u00a0\u00a0\u00a0CodeIgniter\\Database\\BaseBuilder->get()","index":"\u00a0\u00a02\u00a0\u00a0\u00a0\u00a0"},{"file":"SYSTEMPATH\\BaseModel.php:584","function":"\u00a0\u00a0\u00a0\u00a0\u00a0\u00a0\u00a0\u00a0CodeIgniter\\Model->doFindAll()","index":"\u00a0\u00a03\u00a0\u00a0\u00a0\u00a0"},{"file":"APPPATH\\Controllers\\Anfitrion\\UpdateDelete.php:271","function":"\u00a0\u00a0\u00a0\u00a0\u00a0\u00a0\u00a0\u00a0CodeIgniter\\BaseModel->findAll()","index":"\u00a0\u00a04\u00a0\u00a0\u00a0\u00a0"},{"file":"SYSTEMPATH\\CodeIgniter.php:825","function":"\u00a0\u00a0\u00a0\u00a0\u00a0\u00a0\u00a0\u00a0App\\Controllers\\Anfitrion\\UpdateDelete->ActualizarServicio()","index":"\u00a0\u00a05\u00a0\u00a0\u00a0\u00a0"},{"file":"SYSTEMPATH\\CodeIgniter.php:412","function":"\u00a0\u00a0\u00a0\u00a0\u00a0\u00a0\u00a0\u00a0CodeIgniter\\CodeIgniter->runController()","index":"\u00a0\u00a06\u00a0\u00a0\u00a0\u00a0"},{"file":"SYSTEMPATH\\CodeIgniter.php:320","function":"\u00a0\u00a0\u00a0\u00a0\u00a0\u00a0\u00a0\u00a0CodeIgniter\\CodeIgniter->handleRequest()","index":"\u00a0\u00a07\u00a0\u00a0\u00a0\u00a0"},{"file":"FCPATH\\index.php:37","function":"\u00a0\u00a0\u00a0\u00a0\u00a0\u00a0\u00a0\u00a0CodeIgniter\\CodeIgniter->run()","index":"\u00a0\u00a08\u00a0\u00a0\u00a0\u00a0"}],"trace-file":"APPPATH\\Controllers\\Anfitrion\\UpdateDelete.php:271","qid":"7493230477a82535c4e1cbcf8e73ea07"},{"hover":"","class":"","duration":"0.53 ms","sql":"<strong>SELECT<\/strong> `idSubServicio`\n<strong>FROM<\/strong> `tbl_guardar_sub_servicios`\n<strong>WHERE<\/strong> `idServicio` = &#039;2&#039;","trace":[{"file":"SYSTEMPATH\\Database\\BaseBuilder.php:1455","function":"\u00a0\u00a0\u00a0\u00a0\u00a0\u00a0\u00a0\u00a0CodeIgniter\\Database\\BaseConnection->query()","index":"\u00a0\u00a01\u00a0\u00a0\u00a0\u00a0"},{"file":"SYSTEMPATH\\Model.php:145","function":"\u00a0\u00a0\u00a0\u00a0\u00a0\u00a0\u00a0\u00a0CodeIgniter\\Database\\BaseBuilder->get()","index":"\u00a0\u00a02\u00a0\u00a0\u00a0\u00a0"},{"file":"SYSTEMPATH\\BaseModel.php:523","function":"\u00a0\u00a0\u00a0\u00a0\u00a0\u00a0\u00a0\u00a0CodeIgniter\\Model->doFind()","index":"\u00a0\u00a03\u00a0\u00a0\u00a0\u00a0"},{"file":"SYSTEMPATH\\Model.php:161","function":"\u00a0\u00a0\u00a0\u00a0\u00a0\u00a0\u00a0\u00a0CodeIgniter\\BaseModel->find()","index":"\u00a0\u00a04\u00a0\u00a0\u00a0\u00a0"},{"file":"SYSTEMPATH\\BaseModel.php:554","function":"\u00a0\u00a0\u00a0\u00a0\u00a0\u00a0\u00a0\u00a0CodeIgniter\\Model->doFindColumn()","index":"\u00a0\u00a05\u00a0\u00a0\u00a0\u00a0"},{"file":"APPPATH\\Controllers\\Anfitrion\\UpdateDelete.php:272","function":"\u00a0\u00a0\u00a0\u00a0\u00a0\u00a0\u00a0\u00a0CodeIgniter\\BaseModel->findColumn()","index":"\u00a0\u00a06\u00a0\u00a0\u00a0\u00a0"},{"file":"SYSTEMPATH\\CodeIgniter.php:825","function":"\u00a0\u00a0\u00a0\u00a0\u00a0\u00a0\u00a0\u00a0App\\Controllers\\Anfitrion\\UpdateDelete->ActualizarServicio()","index":"\u00a0\u00a07\u00a0\u00a0\u00a0\u00a0"},{"file":"SYSTEMPATH\\CodeIgniter.php:412","function":"\u00a0\u00a0\u00a0\u00a0\u00a0\u00a0\u00a0\u00a0CodeIgniter\\CodeIgniter->runController()","index":"\u00a0\u00a08\u00a0\u00a0\u00a0\u00a0"},{"file":"SYSTEMPATH\\CodeIgniter.php:320","function":"\u00a0\u00a0\u00a0\u00a0\u00a0\u00a0\u00a0\u00a0CodeIgniter\\CodeIgniter->handleRequest()","index":"\u00a0\u00a09\u00a0\u00a0\u00a0\u00a0"},{"file":"FCPATH\\index.php:37","function":"\u00a0\u00a0\u00a0\u00a0\u00a0\u00a0\u00a0\u00a0CodeIgniter\\CodeIgniter->run()","index":"\u00a010\u00a0\u00a0\u00a0\u00a0"}],"trace-file":"APPPATH\\Controllers\\Anfitrion\\UpdateDelete.php:272","qid":"b473f874f08a3e205b5466f21986990f"},{"hover":"","class":"","duration":"2.38 ms","sql":"<strong>SELECT<\/strong> *\n<strong>FROM<\/strong> `tbl_guardar_reglas_servicios`\n<strong>WHERE<\/strong> `idServicio` = &#039;2&#039;","trace":[{"file":"SYSTEMPATH\\Database\\BaseBuilder.php:1455","function":"\u00a0\u00a0\u00a0\u00a0\u00a0\u00a0\u00a0\u00a0CodeIgniter\\Database\\BaseConnection->query()","index":"\u00a0\u00a01\u00a0\u00a0\u00a0\u00a0"},{"file":"SYSTEMPATH\\Model.php:183","function":"\u00a0\u00a0\u00a0\u00a0\u00a0\u00a0\u00a0\u00a0CodeIgniter\\Database\\BaseBuilder->get()","index":"\u00a0\u00a02\u00a0\u00a0\u00a0\u00a0"},{"file":"SYSTEMPATH\\BaseModel.php:584","function":"\u00a0\u00a0\u00a0\u00a0\u00a0\u00a0\u00a0\u00a0CodeIgniter\\Model->doFindAll()","index":"\u00a0\u00a03\u00a0\u00a0\u00a0\u00a0"},{"file":"APPPATH\\Controllers\\Anfitrion\\UpdateDelete.php:301","function":"\u00a0\u00a0\u00a0\u00a0\u00a0\u00a0\u00a0\u00a0CodeIgniter\\BaseModel->findAll()","index":"\u00a0\u00a04\u00a0\u00a0\u00a0\u00a0"},{"file":"SYSTEMPATH\\CodeIgniter.php:825","function":"\u00a0\u00a0\u00a0\u00a0\u00a0\u00a0\u00a0\u00a0App\\Controllers\\Anfitrion\\UpdateDelete->ActualizarServicio()","index":"\u00a0\u00a05\u00a0\u00a0\u00a0\u00a0"},{"file":"SYSTEMPATH\\CodeIgniter.php:412","function":"\u00a0\u00a0\u00a0\u00a0\u00a0\u00a0\u00a0\u00a0CodeIgniter\\CodeIgniter->runController()","index":"\u00a0\u00a06\u00a0\u00a0\u00a0\u00a0"},{"file":"SYSTEMPATH\\CodeIgniter.php:320","function":"\u00a0\u00a0\u00a0\u00a0\u00a0\u00a0\u00a0\u00a0CodeIgniter\\CodeIgniter->handleRequest()","index":"\u00a0\u00a07\u00a0\u00a0\u00a0\u00a0"},{"file":"FCPATH\\index.php:37","function":"\u00a0\u00a0\u00a0\u00a0\u00a0\u00a0\u00a0\u00a0CodeIgniter\\CodeIgniter->run()","index":"\u00a0\u00a08\u00a0\u00a0\u00a0\u00a0"}],"trace-file":"APPPATH\\Controllers\\Anfitrion\\UpdateDelete.php:301","qid":"8efce95def58ca7911aab316d028de62"},{"hover":"","class":"","duration":"0.47 ms","sql":"<strong>SELECT<\/strong> `idReglaServicio`\n<strong>FROM<\/strong> `tbl_guardar_reglas_servicios`\n<strong>WHERE<\/strong> `idServicio` = &#039;2&#039;","trace":[{"file":"SYSTEMPATH\\Database\\BaseBuilder.php:1455","function":"\u00a0\u00a0\u00a0\u00a0\u00a0\u00a0\u00a0\u00a0CodeIgniter\\Database\\BaseConnection->query()","index":"\u00a0\u00a01\u00a0\u00a0\u00a0\u00a0"},{"file":"SYSTEMPATH\\Model.php:145","function":"\u00a0\u00a0\u00a0\u00a0\u00a0\u00a0\u00a0\u00a0CodeIgniter\\Database\\BaseBuilder->get()","index":"\u00a0\u00a02\u00a0\u00a0\u00a0\u00a0"},{"file":"SYSTEMPATH\\BaseModel.php:523","function":"\u00a0\u00a0\u00a0\u00a0\u00a0\u00a0\u00a0\u00a0CodeIgniter\\Model->doFind()","index":"\u00a0\u00a03\u00a0\u00a0\u00a0\u00a0"},{"file":"SYSTEMPATH\\Model.php:161","function":"\u00a0\u00a0\u00a0\u00a0\u00a0\u00a0\u00a0\u00a0CodeIgniter\\BaseModel->find()","index":"\u00a0\u00a04\u00a0\u00a0\u00a0\u00a0"},{"file":"SYSTEMPATH\\BaseModel.php:554","function":"\u00a0\u00a0\u00a0\u00a0\u00a0\u00a0\u00a0\u00a0CodeIgniter\\Model->doFindColumn()","index":"\u00a0\u00a05\u00a0\u00a0\u00a0\u00a0"},{"file":"APPPATH\\Controllers\\Anfitrion\\UpdateDelete.php:302","function":"\u00a0\u00a0\u00a0\u00a0\u00a0\u00a0\u00a0\u00a0CodeIgniter\\BaseModel->findColumn()","index":"\u00a0\u00a06\u00a0\u00a0\u00a0\u00a0"},{"file":"SYSTEMPATH\\CodeIgniter.php:825","function":"\u00a0\u00a0\u00a0\u00a0\u00a0\u00a0\u00a0\u00a0App\\Controllers\\Anfitrion\\UpdateDelete->ActualizarServicio()","index":"\u00a0\u00a07\u00a0\u00a0\u00a0\u00a0"},{"file":"SYSTEMPATH\\CodeIgniter.php:412","function":"\u00a0\u00a0\u00a0\u00a0\u00a0\u00a0\u00a0\u00a0CodeIgniter\\CodeIgniter->runController()","index":"\u00a0\u00a08\u00a0\u00a0\u00a0\u00a0"},{"file":"SYSTEMPATH\\CodeIgniter.php:320","function":"\u00a0\u00a0\u00a0\u00a0\u00a0\u00a0\u00a0\u00a0CodeIgniter\\CodeIgniter->handleRequest()","index":"\u00a0\u00a09\u00a0\u00a0\u00a0\u00a0"},{"file":"FCPATH\\index.php:37","function":"\u00a0\u00a0\u00a0\u00a0\u00a0\u00a0\u00a0\u00a0CodeIgniter\\CodeIgniter->run()","index":"\u00a010\u00a0\u00a0\u00a0\u00a0"}],"trace-file":"APPPATH\\Controllers\\Anfitrion\\UpdateDelete.php:302","qid":"62ed654516bbea7969df6b22ec3f779b"},{"hover":"","class":"","duration":"2.48 ms","sql":"<strong>SELECT<\/strong> *\n<strong>FROM<\/strong> `tbl_guardar_salud_y_seguridad`\n<strong>WHERE<\/strong> `idServicio` = &#039;2&#039;","trace":[{"file":"SYSTEMPATH\\Database\\BaseBuilder.php:1455","function":"\u00a0\u00a0\u00a0\u00a0\u00a0\u00a0\u00a0\u00a0CodeIgniter\\Database\\BaseConnection->query()","index":"\u00a0\u00a01\u00a0\u00a0\u00a0\u00a0"},{"file":"SYSTEMPATH\\Model.php:183","function":"\u00a0\u00a0\u00a0\u00a0\u00a0\u00a0\u00a0\u00a0CodeIgniter\\Database\\BaseBuilder->get()","index":"\u00a0\u00a02\u00a0\u00a0\u00a0\u00a0"},{"file":"SYSTEMPATH\\BaseModel.php:584","function":"\u00a0\u00a0\u00a0\u00a0\u00a0\u00a0\u00a0\u00a0CodeIgniter\\Model->doFindAll()","index":"\u00a0\u00a03\u00a0\u00a0\u00a0\u00a0"},{"file":"APPPATH\\Controllers\\Anfitrion\\UpdateDelete.php:331","function":"\u00a0\u00a0\u00a0\u00a0\u00a0\u00a0\u00a0\u00a0CodeIgniter\\BaseModel->findAll()","index":"\u00a0\u00a04\u00a0\u00a0\u00a0\u00a0"},{"file":"SYSTEMPATH\\CodeIgniter.php:825","function":"\u00a0\u00a0\u00a0\u00a0\u00a0\u00a0\u00a0\u00a0App\\Controllers\\Anfitrion\\UpdateDelete->ActualizarServicio()","index":"\u00a0\u00a05\u00a0\u00a0\u00a0\u00a0"},{"file":"SYSTEMPATH\\CodeIgniter.php:412","function":"\u00a0\u00a0\u00a0\u00a0\u00a0\u00a0\u00a0\u00a0CodeIgniter\\CodeIgniter->runController()","index":"\u00a0\u00a06\u00a0\u00a0\u00a0\u00a0"},{"file":"SYSTEMPATH\\CodeIgniter.php:320","function":"\u00a0\u00a0\u00a0\u00a0\u00a0\u00a0\u00a0\u00a0CodeIgniter\\CodeIgniter->handleRequest()","index":"\u00a0\u00a07\u00a0\u00a0\u00a0\u00a0"},{"file":"FCPATH\\index.php:37","function":"\u00a0\u00a0\u00a0\u00a0\u00a0\u00a0\u00a0\u00a0CodeIgniter\\CodeIgniter->run()","index":"\u00a0\u00a08\u00a0\u00a0\u00a0\u00a0"}],"trace-file":"APPPATH\\Controllers\\Anfitrion\\UpdateDelete.php:331","qid":"366382a612034c6019ba5b4d6e507e0c"},{"hover":"","class":"","duration":"0.31 ms","sql":"<strong>SELECT<\/strong> `idSaludSeguridad`\n<strong>FROM<\/strong> `tbl_guardar_salud_y_seguridad`\n<strong>WHERE<\/strong> `idServicio` = &#039;2&#039;","trace":[{"file":"SYSTEMPATH\\Database\\BaseBuilder.php:1455","function":"\u00a0\u00a0\u00a0\u00a0\u00a0\u00a0\u00a0\u00a0CodeIgniter\\Database\\BaseConnection->query()","index":"\u00a0\u00a01\u00a0\u00a0\u00a0\u00a0"},{"file":"SYSTEMPATH\\Model.php:145","function":"\u00a0\u00a0\u00a0\u00a0\u00a0\u00a0\u00a0\u00a0CodeIgniter\\Database\\BaseBuilder->get()","index":"\u00a0\u00a02\u00a0\u00a0\u00a0\u00a0"},{"file":"SYSTEMPATH\\BaseModel.php:523","function":"\u00a0\u00a0\u00a0\u00a0\u00a0\u00a0\u00a0\u00a0CodeIgniter\\Model->doFind()","index":"\u00a0\u00a03\u00a0\u00a0\u00a0\u00a0"},{"file":"SYSTEMPATH\\Model.php:161","function":"\u00a0\u00a0\u00a0\u00a0\u00a0\u00a0\u00a0\u00a0CodeIgniter\\BaseModel->find()","index":"\u00a0\u00a04\u00a0\u00a0\u00a0\u00a0"},{"file":"SYSTEMPATH\\BaseModel.php:554","function":"\u00a0\u00a0\u00a0\u00a0\u00a0\u00a0\u00a0\u00a0CodeIgniter\\Model->doFindColumn()","index":"\u00a0\u00a05\u00a0\u00a0\u00a0\u00a0"},{"file":"APPPATH\\Controllers\\Anfitrion\\UpdateDelete.php:332","function":"\u00a0\u00a0\u00a0\u00a0\u00a0\u00a0\u00a0\u00a0CodeIgniter\\BaseModel->findColumn()","index":"\u00a0\u00a06\u00a0\u00a0\u00a0\u00a0"},{"file":"SYSTEMPATH\\CodeIgniter.php:825","function":"\u00a0\u00a0\u00a0\u00a0\u00a0\u00a0\u00a0\u00a0App\\Controllers\\Anfitrion\\UpdateDelete->ActualizarServicio()","index":"\u00a0\u00a07\u00a0\u00a0\u00a0\u00a0"},{"file":"SYSTEMPATH\\CodeIgniter.php:412","function":"\u00a0\u00a0\u00a0\u00a0\u00a0\u00a0\u00a0\u00a0CodeIgniter\\CodeIgniter->runController()","index":"\u00a0\u00a08\u00a0\u00a0\u00a0\u00a0"},{"file":"SYSTEMPATH\\CodeIgniter.php:320","function":"\u00a0\u00a0\u00a0\u00a0\u00a0\u00a0\u00a0\u00a0CodeIgniter\\CodeIgniter->handleRequest()","index":"\u00a0\u00a09\u00a0\u00a0\u00a0\u00a0"},{"file":"FCPATH\\index.php:37","function":"\u00a0\u00a0\u00a0\u00a0\u00a0\u00a0\u00a0\u00a0CodeIgniter\\CodeIgniter->run()","index":"\u00a010\u00a0\u00a0\u00a0\u00a0"}],"trace-file":"APPPATH\\Controllers\\Anfitrion\\UpdateDelete.php:332","qid":"d18ef7ad931f6e9a304238bf0f9f1c6f"},{"hover":"","class":"","duration":"2.01 ms","sql":"DELETE <strong>FROM<\/strong> `tbl_guardar_salud_y_seguridad`\n<strong>WHERE<\/strong> `idGuardar` <strong>IN<\/strong> (&#039;8&#039;)","trace":[{"file":"SYSTEMPATH\\Database\\BaseBuilder.php:2225","function":"\u00a0\u00a0\u00a0\u00a0\u00a0\u00a0\u00a0\u00a0CodeIgniter\\Database\\BaseConnection->query()","index":"\u00a0\u00a01\u00a0\u00a0\u00a0\u00a0"},{"file":"SYSTEMPATH\\Model.php:359","function":"\u00a0\u00a0\u00a0\u00a0\u00a0\u00a0\u00a0\u00a0CodeIgniter\\Database\\BaseBuilder->delete()","index":"\u00a0\u00a02\u00a0\u00a0\u00a0\u00a0"},{"file":"SYSTEMPATH\\BaseModel.php:963","function":"\u00a0\u00a0\u00a0\u00a0\u00a0\u00a0\u00a0\u00a0CodeIgniter\\Model->doDelete()","index":"\u00a0\u00a03\u00a0\u00a0\u00a0\u00a0"},{"file":"APPPATH\\Controllers\\Anfitrion\\UpdateDelete.php:340","function":"\u00a0\u00a0\u00a0\u00a0\u00a0\u00a0\u00a0\u00a0CodeIgniter\\BaseModel->delete()","index":"\u00a0\u00a04\u00a0\u00a0\u00a0\u00a0"},{"file":"SYSTEMPATH\\CodeIgniter.php:825","function":"\u00a0\u00a0\u00a0\u00a0\u00a0\u00a0\u00a0\u00a0App\\Controllers\\Anfitrion\\UpdateDelete->ActualizarServicio()","index":"\u00a0\u00a05\u00a0\u00a0\u00a0\u00a0"},{"file":"SYSTEMPATH\\CodeIgniter.php:412","function":"\u00a0\u00a0\u00a0\u00a0\u00a0\u00a0\u00a0\u00a0CodeIgniter\\CodeIgniter->runController()","index":"\u00a0\u00a06\u00a0\u00a0\u00a0\u00a0"},{"file":"SYSTEMPATH\\CodeIgniter.php:320","function":"\u00a0\u00a0\u00a0\u00a0\u00a0\u00a0\u00a0\u00a0CodeIgniter\\CodeIgniter->handleRequest()","index":"\u00a0\u00a07\u00a0\u00a0\u00a0\u00a0"},{"file":"FCPATH\\index.php:37","function":"\u00a0\u00a0\u00a0\u00a0\u00a0\u00a0\u00a0\u00a0CodeIgniter\\CodeIgniter->run()","index":"\u00a0\u00a08\u00a0\u00a0\u00a0\u00a0"}],"trace-file":"APPPATH\\Controllers\\Anfitrion\\UpdateDelete.php:340","qid":"d035461cb777bb90cdd425a6b9480c87"},{"hover":"","class":"","duration":"1.21 ms","sql":"DELETE <strong>FROM<\/strong> `tbl_guardar_salud_y_seguridad`\n<strong>WHERE<\/strong> `idGuardar` <strong>IN<\/strong> (&#039;9&#039;)","trace":[{"file":"SYSTEMPATH\\Database\\BaseBuilder.php:2225","function":"\u00a0\u00a0\u00a0\u00a0\u00a0\u00a0\u00a0\u00a0CodeIgniter\\Database\\BaseConnection->query()","index":"\u00a0\u00a01\u00a0\u00a0\u00a0\u00a0"},{"file":"SYSTEMPATH\\Model.php:359","function":"\u00a0\u00a0\u00a0\u00a0\u00a0\u00a0\u00a0\u00a0CodeIgniter\\Database\\BaseBuilder->delete()","index":"\u00a0\u00a02\u00a0\u00a0\u00a0\u00a0"},{"file":"SYSTEMPATH\\BaseModel.php:963","function":"\u00a0\u00a0\u00a0\u00a0\u00a0\u00a0\u00a0\u00a0CodeIgniter\\Model->doDelete()","index":"\u00a0\u00a03\u00a0\u00a0\u00a0\u00a0"},{"file":"APPPATH\\Controllers\\Anfitrion\\UpdateDelete.php:340","function":"\u00a0\u00a0\u00a0\u00a0\u00a0\u00a0\u00a0\u00a0CodeIgniter\\BaseModel->delete()","index":"\u00a0\u00a04\u00a0\u00a0\u00a0\u00a0"},{"file":"SYSTEMPATH\\CodeIgniter.php:825","function":"\u00a0\u00a0\u00a0\u00a0\u00a0\u00a0\u00a0\u00a0App\\Controllers\\Anfitrion\\UpdateDelete->ActualizarServicio()","index":"\u00a0\u00a05\u00a0\u00a0\u00a0\u00a0"},{"file":"SYSTEMPATH\\CodeIgniter.php:412","function":"\u00a0\u00a0\u00a0\u00a0\u00a0\u00a0\u00a0\u00a0CodeIgniter\\CodeIgniter->runController()","index":"\u00a0\u00a06\u00a0\u00a0\u00a0\u00a0"},{"file":"SYSTEMPATH\\CodeIgniter.php:320","function":"\u00a0\u00a0\u00a0\u00a0\u00a0\u00a0\u00a0\u00a0CodeIgniter\\CodeIgniter->handleRequest()","index":"\u00a0\u00a07\u00a0\u00a0\u00a0\u00a0"},{"file":"FCPATH\\index.php:37","function":"\u00a0\u00a0\u00a0\u00a0\u00a0\u00a0\u00a0\u00a0CodeIgniter\\CodeIgniter->run()","index":"\u00a0\u00a08\u00a0\u00a0\u00a0\u00a0"}],"trace-file":"APPPATH\\Controllers\\Anfitrion\\UpdateDelete.php:340","qid":"2c3a64379adf62b8841f52c91e786cbe"},{"hover":"","class":"","duration":"8.15 ms","sql":"<strong>SELECT<\/strong> *\n<strong>FROM<\/strong> `tbl_guardar_politicas_de_cancelacion`\n<strong>WHERE<\/strong> `idServicio` = &#039;2&#039;","trace":[{"file":"SYSTEMPATH\\Database\\BaseBuilder.php:1455","function":"\u00a0\u00a0\u00a0\u00a0\u00a0\u00a0\u00a0\u00a0CodeIgniter\\Database\\BaseConnection->query()","index":"\u00a0\u00a01\u00a0\u00a0\u00a0\u00a0"},{"file":"SYSTEMPATH\\Model.php:183","function":"\u00a0\u00a0\u00a0\u00a0\u00a0\u00a0\u00a0\u00a0CodeIgniter\\Database\\BaseBuilder->get()","index":"\u00a0\u00a02\u00a0\u00a0\u00a0\u00a0"},{"file":"SYSTEMPATH\\BaseModel.php:584","function":"\u00a0\u00a0\u00a0\u00a0\u00a0\u00a0\u00a0\u00a0CodeIgniter\\Model->doFindAll()","index":"\u00a0\u00a03\u00a0\u00a0\u00a0\u00a0"},{"file":"APPPATH\\Controllers\\Anfitrion\\UpdateDelete.php:361","function":"\u00a0\u00a0\u00a0\u00a0\u00a0\u00a0\u00a0\u00a0CodeIgniter\\BaseModel->findAll()","index":"\u00a0\u00a04\u00a0\u00a0\u00a0\u00a0"},{"file":"SYSTEMPATH\\CodeIgniter.php:825","function":"\u00a0\u00a0\u00a0\u00a0\u00a0\u00a0\u00a0\u00a0App\\Controllers\\Anfitrion\\UpdateDelete->ActualizarServicio()","index":"\u00a0\u00a05\u00a0\u00a0\u00a0\u00a0"},{"file":"SYSTEMPATH\\CodeIgniter.php:412","function":"\u00a0\u00a0\u00a0\u00a0\u00a0\u00a0\u00a0\u00a0CodeIgniter\\CodeIgniter->runController()","index":"\u00a0\u00a06\u00a0\u00a0\u00a0\u00a0"},{"file":"SYSTEMPATH\\CodeIgniter.php:320","function":"\u00a0\u00a0\u00a0\u00a0\u00a0\u00a0\u00a0\u00a0CodeIgniter\\CodeIgniter->handleRequest()","index":"\u00a0\u00a07\u00a0\u00a0\u00a0\u00a0"},{"file":"FCPATH\\index.php:37","function":"\u00a0\u00a0\u00a0\u00a0\u00a0\u00a0\u00a0\u00a0CodeIgniter\\CodeIgniter->run()","index":"\u00a0\u00a08\u00a0\u00a0\u00a0\u00a0"}],"trace-file":"APPPATH\\Controllers\\Anfitrion\\UpdateDelete.php:361","qid":"d15b194c45a0697956f7e18ebd7b61d4"},{"hover":"","class":"","duration":"0.3 ms","sql":"<strong>SELECT<\/strong> `idPoliticaCancelacion`\n<strong>FROM<\/strong> `tbl_guardar_politicas_de_cancelacion`\n<strong>WHERE<\/strong> `idServicio` = &#039;2&#039;","trace":[{"file":"SYSTEMPATH\\Database\\BaseBuilder.php:1455","function":"\u00a0\u00a0\u00a0\u00a0\u00a0\u00a0\u00a0\u00a0CodeIgniter\\Database\\BaseConnection->query()","index":"\u00a0\u00a01\u00a0\u00a0\u00a0\u00a0"},{"file":"SYSTEMPATH\\Model.php:145","function":"\u00a0\u00a0\u00a0\u00a0\u00a0\u00a0\u00a0\u00a0CodeIgniter\\Database\\BaseBuilder->get()","index":"\u00a0\u00a02\u00a0\u00a0\u00a0\u00a0"},{"file":"SYSTEMPATH\\BaseModel.php:523","function":"\u00a0\u00a0\u00a0\u00a0\u00a0\u00a0\u00a0\u00a0CodeIgniter\\Model->doFind()","index":"\u00a0\u00a03\u00a0\u00a0\u00a0\u00a0"},{"file":"SYSTEMPATH\\Model.php:161","function":"\u00a0\u00a0\u00a0\u00a0\u00a0\u00a0\u00a0\u00a0CodeIgniter\\BaseModel->find()","index":"\u00a0\u00a04\u00a0\u00a0\u00a0\u00a0"},{"file":"SYSTEMPATH\\BaseModel.php:554","function":"\u00a0\u00a0\u00a0\u00a0\u00a0\u00a0\u00a0\u00a0CodeIgniter\\Model->doFindColumn()","index":"\u00a0\u00a05\u00a0\u00a0\u00a0\u00a0"},{"file":"APPPATH\\Controllers\\Anfitrion\\UpdateDelete.php:362","function":"\u00a0\u00a0\u00a0\u00a0\u00a0\u00a0\u00a0\u00a0CodeIgniter\\BaseModel->findColumn()","index":"\u00a0\u00a06\u00a0\u00a0\u00a0\u00a0"},{"file":"SYSTEMPATH\\CodeIgniter.php:825","function":"\u00a0\u00a0\u00a0\u00a0\u00a0\u00a0\u00a0\u00a0App\\Controllers\\Anfitrion\\UpdateDelete->ActualizarServicio()","index":"\u00a0\u00a07\u00a0\u00a0\u00a0\u00a0"},{"file":"SYSTEMPATH\\CodeIgniter.php:412","function":"\u00a0\u00a0\u00a0\u00a0\u00a0\u00a0\u00a0\u00a0CodeIgniter\\CodeIgniter->runController()","index":"\u00a0\u00a08\u00a0\u00a0\u00a0\u00a0"},{"file":"SYSTEMPATH\\CodeIgniter.php:320","function":"\u00a0\u00a0\u00a0\u00a0\u00a0\u00a0\u00a0\u00a0CodeIgniter\\CodeIgniter->handleRequest()","index":"\u00a0\u00a09\u00a0\u00a0\u00a0\u00a0"},{"file":"FCPATH\\index.php:37","function":"\u00a0\u00a0\u00a0\u00a0\u00a0\u00a0\u00a0\u00a0CodeIgniter\\CodeIgniter->run()","index":"\u00a010\u00a0\u00a0\u00a0\u00a0"}],"trace-file":"APPPATH\\Controllers\\Anfitrion\\UpdateDelete.php:362","qid":"69ec92cd0f3d0c2f5cc81eee255a1745"},{"hover":"","class":"","duration":"2.47 ms","sql":"<strong>SELECT<\/strong> `idHuesped`\n<strong>FROM<\/strong> `tbl_huespedes`\n<strong>WHERE<\/strong> `idServicio` = &#039;2&#039;","trace":[{"file":"SYSTEMPATH\\Database\\BaseBuilder.php:1455","function":"\u00a0\u00a0\u00a0\u00a0\u00a0\u00a0\u00a0\u00a0CodeIgniter\\Database\\BaseConnection->query()","index":"\u00a0\u00a01\u00a0\u00a0\u00a0\u00a0"},{"file":"SYSTEMPATH\\Model.php:145","function":"\u00a0\u00a0\u00a0\u00a0\u00a0\u00a0\u00a0\u00a0CodeIgniter\\Database\\BaseBuilder->get()","index":"\u00a0\u00a02\u00a0\u00a0\u00a0\u00a0"},{"file":"SYSTEMPATH\\BaseModel.php:523","function":"\u00a0\u00a0\u00a0\u00a0\u00a0\u00a0\u00a0\u00a0CodeIgniter\\Model->doFind()","index":"\u00a0\u00a03\u00a0\u00a0\u00a0\u00a0"},{"file":"SYSTEMPATH\\Model.php:161","function":"\u00a0\u00a0\u00a0\u00a0\u00a0\u00a0\u00a0\u00a0CodeIgniter\\BaseModel->find()","index":"\u00a0\u00a04\u00a0\u00a0\u00a0\u00a0"},{"file":"SYSTEMPATH\\BaseModel.php:554","function":"\u00a0\u00a0\u00a0\u00a0\u00a0\u00a0\u00a0\u00a0CodeIgniter\\Model->doFindColumn()","index":"\u00a0\u00a05\u00a0\u00a0\u00a0\u00a0"},{"file":"APPPATH\\Controllers\\Anfitrion\\UpdateDelete.php:389","function":"\u00a0\u00a0\u00a0\u00a0\u00a0\u00a0\u00a0\u00a0CodeIgniter\\BaseModel->findColumn()","index":"\u00a0\u00a06\u00a0\u00a0\u00a0\u00a0"},{"file":"SYSTEMPATH\\CodeIgniter.php:825","function":"\u00a0\u00a0\u00a0\u00a0\u00a0\u00a0\u00a0\u00a0App\\Controllers\\Anfitrion\\UpdateDelete->ActualizarServicio()","index":"\u00a0\u00a07\u00a0\u00a0\u00a0\u00a0"},{"file":"SYSTEMPATH\\CodeIgniter.php:412","function":"\u00a0\u00a0\u00a0\u00a0\u00a0\u00a0\u00a0\u00a0CodeIgniter\\CodeIgniter->runController()","index":"\u00a0\u00a08\u00a0\u00a0\u00a0\u00a0"},{"file":"SYSTEMPATH\\CodeIgniter.php:320","function":"\u00a0\u00a0\u00a0\u00a0\u00a0\u00a0\u00a0\u00a0CodeIgniter\\CodeIgniter->handleRequest()","index":"\u00a0\u00a09\u00a0\u00a0\u00a0\u00a0"},{"file":"FCPATH\\index.php:37","function":"\u00a0\u00a0\u00a0\u00a0\u00a0\u00a0\u00a0\u00a0CodeIgniter\\CodeIgniter->run()","index":"\u00a010\u00a0\u00a0\u00a0\u00a0"}],"trace-file":"APPPATH\\Controllers\\Anfitrion\\UpdateDelete.php:389","qid":"748b8e17a0dae06c8363484b5c99128b"},{"hover":"","class":"","duration":"1.34 ms","sql":"<strong>UPDATE<\/strong> `tbl_huespedes` SET `adulto` = &#039;2&#039;, `bebes` = &#039;1&#039;, `menores` = &#039;3&#039;, `mascotas` = &#039;1&#039;, `idServicio` = &#039;2&#039;, `date_update` = &#039;2022-10-25 09:45:07&#039;\n<strong>WHERE<\/strong> `tbl_huespedes`.`idHuesped` <strong>IN<\/strong> (&#039;2&#039;)","trace":[{"file":"SYSTEMPATH\\Database\\BaseBuilder.php:1913","function":"\u00a0\u00a0\u00a0\u00a0\u00a0\u00a0\u00a0\u00a0CodeIgniter\\Database\\BaseConnection->query()","index":"\u00a0\u00a01\u00a0\u00a0\u00a0\u00a0"},{"file":"SYSTEMPATH\\Model.php:298","function":"\u00a0\u00a0\u00a0\u00a0\u00a0\u00a0\u00a0\u00a0CodeIgniter\\Database\\BaseBuilder->update()","index":"\u00a0\u00a02\u00a0\u00a0\u00a0\u00a0"},{"file":"SYSTEMPATH\\BaseModel.php:865","function":"\u00a0\u00a0\u00a0\u00a0\u00a0\u00a0\u00a0\u00a0CodeIgniter\\Model->doUpdate()","index":"\u00a0\u00a03\u00a0\u00a0\u00a0\u00a0"},{"file":"SYSTEMPATH\\Model.php:651","function":"\u00a0\u00a0\u00a0\u00a0\u00a0\u00a0\u00a0\u00a0CodeIgniter\\BaseModel->update()","index":"\u00a0\u00a04\u00a0\u00a0\u00a0\u00a0"},{"file":"SYSTEMPATH\\BaseModel.php:656","function":"\u00a0\u00a0\u00a0\u00a0\u00a0\u00a0\u00a0\u00a0CodeIgniter\\Model->update()","index":"\u00a0\u00a05\u00a0\u00a0\u00a0\u00a0"},{"file":"APPPATH\\Controllers\\Anfitrion\\UpdateDelete.php:400","function":"\u00a0\u00a0\u00a0\u00a0\u00a0\u00a0\u00a0\u00a0CodeIgniter\\BaseModel->save()","index":"\u00a0\u00a06\u00a0\u00a0\u00a0\u00a0"},{"file":"SYSTEMPATH\\CodeIgniter.php:825","function":"\u00a0\u00a0\u00a0\u00a0\u00a0\u00a0\u00a0\u00a0App\\Controllers\\Anfitrion\\UpdateDelete->ActualizarServicio()","index":"\u00a0\u00a07\u00a0\u00a0\u00a0\u00a0"},{"file":"SYSTEMPATH\\CodeIgniter.php:412","function":"\u00a0\u00a0\u00a0\u00a0\u00a0\u00a0\u00a0\u00a0CodeIgniter\\CodeIgniter->runController()","index":"\u00a0\u00a08\u00a0\u00a0\u00a0\u00a0"},{"file":"SYSTEMPATH\\CodeIgniter.php:320","function":"\u00a0\u00a0\u00a0\u00a0\u00a0\u00a0\u00a0\u00a0CodeIgniter\\CodeIgniter->handleRequest()","index":"\u00a0\u00a09\u00a0\u00a0\u00a0\u00a0"},{"file":"FCPATH\\index.php:37","function":"\u00a0\u00a0\u00a0\u00a0\u00a0\u00a0\u00a0\u00a0CodeIgniter\\CodeIgniter->run()","index":"\u00a010\u00a0\u00a0\u00a0\u00a0"}],"trace-file":"APPPATH\\Controllers\\Anfitrion\\UpdateDelete.php:400","qid":"870f10b21139ecb66713fa512cbea20b"}]},"badgeValue":23,"isEmpty":false,"hasTabContent":true,"hasLabel":false,"icon":"data:image\/png;base64,iVBORw0KGgoAAAANSUhEUgAAABgAAAAYCAYAAADgdz34AAAAAXNSR0IArs4c6QAAAARnQU1BAACxjwv8YQUAAAAJcEhZcwAADsMAAA7DAcdvqGQAAADMSURBVEhLY6A3YExLSwsA4nIycQDIDIhRWEBqamo\/UNF\/SjDQjF6ocZgAKPkRiFeEhoYyQ4WIBiA9QAuWAPEHqBAmgLqgHcolGQD1V4DMgHIxwbCxYD+QBqcKINseKo6eWrBioPrtQBq\/BcgY5ht0cUIYbBg2AJKkRxCNWkDQgtFUNJwtABr+F6igE8olGQD114HMgHIxAVDyAhA\/AlpSA8RYUwoeXAPVex5qHCbIyMgwBCkAuQJIY00huDBUz\/mUlBQDqHGjgBjAwAAACexpph6oHSQAAAAASUVORK5CYII=","hasTimelineData":true,"timelineData":[{"name":"Connecting to Database: \"default\"","component":"Database","start":1666712707.242178,"duration":"0.001712"},{"name":"Query","component":"Database","start":1666712707.245467,"duration":"0.000426","query":"<strong>SELECT<\/strong> *\n<strong>FROM<\/strong> `tbl_usuarios`\n<strong>WHERE<\/strong> `idUsuario` = &#039;1&#039;\n <strong>LIMIT<\/strong> 1"},{"name":"Query","component":"Database","start":1666712707.251723,"duration":"0.000722","query":"<strong>SELECT<\/strong> *\n<strong>FROM<\/strong> `tbl_roles`\n<strong>WHERE<\/strong> `idRol` = &#039;3&#039;"},{"name":"Query","component":"Database","start":1666712707.264677,"duration":"0.003270","query":"<strong>SELECT<\/strong> *\n<strong>FROM<\/strong> `tbl_servicios`"},{"name":"Query","component":"Database","start":1666712707.446058,"duration":"0.001881","query":"<strong>SELECT<\/strong> 1\n<strong>FROM<\/strong> `tbl_tipo_hospedajes`\n<strong>WHERE<\/strong> `idTipoHospedaje` = &#039;1&#039;\n <strong>LIMIT<\/strong> 1"},{"name":"Query","component":"Database","start":1666712707.448336,"duration":"0.003028","query":"<strong>SELECT<\/strong> `idSubServicio`\n<strong>FROM<\/strong> `tbl_sub_servicios`"},{"name":"Query","component":"Database","start":1666712707.451675,"duration":"0.002169","query":"<strong>SELECT<\/strong> `idSaludSeguridad`\n<strong>FROM<\/strong> `tbl_salud_y_seguridad`"},{"name":"Query","component":"Database","start":1666712707.454037,"duration":"0.001963","query":"<strong>SELECT<\/strong> `idReglaServicio`\n<strong>FROM<\/strong> `tbl_reglas_servicios`"},{"name":"Query","component":"Database","start":1666712707.456186,"duration":"0.002434","query":"<strong>SELECT<\/strong> `idPoliticaCancelacion`\n<strong>FROM<\/strong> `tbl_politicas_de_cancelacion`"},{"name":"Query","component":"Database","start":1666712707.458848,"duration":"0.000321","query":"<strong>SELECT<\/strong> `idTarifa`\n<strong>FROM<\/strong> `tbl_servicios`\n<strong>WHERE<\/strong> `idServicio` = &#039;2&#039;"},{"name":"Query","component":"Database","start":1666712707.45941,"duration":"0.003013","query":"<strong>UPDATE<\/strong> `tbl_tarifas` SET `precio` = &#039;100&#039;, `descuento` = &#039;10&#039;, `date_update` = &#039;2022-10-25 09:45:07&#039;\n<strong>WHERE<\/strong> `tbl_tarifas`.`idTarifa` <strong>IN<\/strong> (&#039;2&#039;)"},{"name":"Query","component":"Database","start":1666712707.462662,"duration":"0.001263","query":"<strong>UPDATE<\/strong> `tbl_servicios` SET `nombre` = &#039;Servicio 1&#039;, `descripcion` = &#039;Caba\u00f1a con un clima fresco con temperaturas bajas no encontrada en el pais.&#039;, `idTipoHospedaje` = &#039;1&#039;, `direccion` = &#039;Av. 3 calle poniente&#039;, `disponibilidad` = 0, `date_update` = &#039;2022-10-25 09:45:07&#039;\n<strong>WHERE<\/strong> `tbl_servicios`.`idServicio` <strong>IN<\/strong> (&#039;2&#039;)"},{"name":"Query","component":"Database","start":1666712707.464119,"duration":"0.003445","query":"<strong>SELECT<\/strong> *\n<strong>FROM<\/strong> `tbl_guardar_sub_servicios`\n<strong>WHERE<\/strong> `idServicio` = &#039;2&#039;"},{"name":"Query","component":"Database","start":1666712707.467823,"duration":"0.000526","query":"<strong>SELECT<\/strong> `idSubServicio`\n<strong>FROM<\/strong> `tbl_guardar_sub_servicios`\n<strong>WHERE<\/strong> `idServicio` = &#039;2&#039;"},{"name":"Query","component":"Database","start":1666712707.468976,"duration":"0.002384","query":"<strong>SELECT<\/strong> *\n<strong>FROM<\/strong> `tbl_guardar_reglas_servicios`\n<strong>WHERE<\/strong> `idServicio` = &#039;2&#039;"},{"name":"Query","component":"Database","start":1666712707.471603,"duration":"0.000474","query":"<strong>SELECT<\/strong> `idReglaServicio`\n<strong>FROM<\/strong> `tbl_guardar_reglas_servicios`\n<strong>WHERE<\/strong> `idServicio` = &#039;2&#039;"},{"name":"Query","component":"Database","start":1666712707.472422,"duration":"0.002475","query":"<strong>SELECT<\/strong> *\n<strong>FROM<\/strong> `tbl_guardar_salud_y_seguridad`\n<strong>WHERE<\/strong> `idServicio` = &#039;2&#039;"},{"name":"Query","component":"Database","start":1666712707.475134,"duration":"0.000312","query":"<strong>SELECT<\/strong> `idSaludSeguridad`\n<strong>FROM<\/strong> `tbl_guardar_salud_y_seguridad`\n<strong>WHERE<\/strong> `idServicio` = &#039;2&#039;"},{"name":"Query","component":"Database","start":1666712707.475598,"duration":"0.002010","query":"DELETE <strong>FROM<\/strong> `tbl_guardar_salud_y_seguridad`\n<strong>WHERE<\/strong> `idGuardar` <strong>IN<\/strong> (&#039;8&#039;)"},{"name":"Query","component":"Database","start":1666712707.478041,"duration":"0.001213","query":"DELETE <strong>FROM<\/strong> `tbl_guardar_salud_y_seguridad`\n<strong>WHERE<\/strong> `idGuardar` <strong>IN<\/strong> (&#039;9&#039;)"},{"name":"Query","component":"Database","start":1666712707.479472,"duration":"0.008147","query":"<strong>SELECT<\/strong> *\n<strong>FROM<\/strong> `tbl_guardar_politicas_de_cancelacion`\n<strong>WHERE<\/strong> `idServicio` = &#039;2&#039;"},{"name":"Query","component":"Database","start":1666712707.487851,"duration":"0.000302","query":"<strong>SELECT<\/strong> `idPoliticaCancelacion`\n<strong>FROM<\/strong> `tbl_guardar_politicas_de_cancelacion`\n<strong>WHERE<\/strong> `idServicio` = &#039;2&#039;"},{"name":"Query","component":"Database","start":1666712707.488351,"duration":"0.002466","query":"<strong>SELECT<\/strong> `idHuesped`\n<strong>FROM<\/strong> `tbl_huespedes`\n<strong>WHERE<\/strong> `idServicio` = &#039;2&#039;"},{"name":"Query","component":"Database","start":1666712707.491087,"duration":"0.001342","query":"<strong>UPDATE<\/strong> `tbl_huespedes` SET `adulto` = &#039;2&#039;, `bebes` = &#039;1&#039;, `menores` = &#039;3&#039;, `mascotas` = &#039;1&#039;, `idServicio` = &#039;2&#039;, `date_update` = &#039;2022-10-25 09:45:07&#039;\n<strong>WHERE<\/strong> `tbl_huespedes`.`idHuesped` <strong>IN<\/strong> (&#039;2&#039;)"}]},{"title":"Logs","titleSafe":"logs","titleDetails":"","display":{"logs":[]},"badgeValue":null,"isEmpty":true,"hasTabContent":true,"hasLabel":false,"icon":"data:image\/png;base64,iVBORw0KGgoAAAANSUhEUgAAABgAAAAYCAYAAADgdz34AAAAAXNSR0IArs4c6QAAAARnQU1BAACxjwv8YQUAAAAJcEhZcwAADsMAAA7DAcdvqGQAAACYSURBVEhLYxgFJIHU1FSjtLS0i0D8AYj7gEKMEBkqAaAFF4D4ERCvAFrwH4gDoFIMKSkpFkB+OTEYqgUTACXfA\/GqjIwMQyD9H2hRHlQKJFcBEiMGQ7VgAqCBvUgK32dmZspCpagGGNPT0\/1BLqeF4bQHQJePpiIwhmrBBEADR1MRfgB0+WgqAmOoFkwANHA0FY0CUgEDAwCQ0PUpNB3kqwAAAABJRU5ErkJggg==","hasTimelineData":false,"timelineData":[]},{"title":"Views","titleSafe":"views","titleDetails":"","display":[],"badgeValue":0,"isEmpty":false,"hasTabContent":false,"hasLabel":true,"icon":"data:image\/png;base64,iVBORw0KGgoAAAANSUhEUgAAABgAAAAYCAYAAADgdz34AAAAAXNSR0IArs4c6QAAAARnQU1BAACxjwv8YQUAAAAJcEhZcwAADsMAAA7DAcdvqGQAAADeSURBVEhL7ZSxDcIwEEWNYA0YgGmgyAaJLTcUaaBzQQEVjMEabBQxAdw53zTHiThEovGTfnE\/9rsoRUxhKLOmaa6Uh7X2+UvguLCzVxN1XW9x4EYHzik033Hp3X0LO+DaQG8MDQcuq6qao4qkHuMgQggLvkPLjqh00ZgFDBacMJYFkuwFlH1mshdkZ5JPJERA9JpI6xNCBESvibQ+IURA9JpI6xNCBESvibQ+IURA9DTsuHTOrVFFxixgB\/eUFlU8uKJ0eDBFOu\/9EvoeKnlJS2\/08Tc8NOwQ8sIfMeYFjqKDjdU2sp4AAAAASUVORK5CYII=","hasTimelineData":true,"timelineData":[]},{"title":"Files","titleSafe":"files","titleDetails":"( 151 )","display":{"coreFiles":[{"name":"AutoloadConfig.php","path":"SYSTEMPATH\\Config\\AutoloadConfig.php"},{"name":"Autoloader.php","path":"SYSTEMPATH\\Autoloader\\Autoloader.php"},{"name":"BaseBuilder.php","path":"SYSTEMPATH\\Database\\BaseBuilder.php"},{"name":"BaseCollector.php","path":"SYSTEMPATH\\Debug\\Toolbar\\Collectors\\BaseCollector.php"},{"name":"BaseConfig.php","path":"SYSTEMPATH\\Config\\BaseConfig.php"},{"name":"BaseConnection.php","path":"SYSTEMPATH\\Database\\BaseConnection.php"},{"name":"BaseHandler.php","path":"SYSTEMPATH\\Cache\\Handlers\\BaseHandler.php"},{"name":"BaseHandler.php","path":"SYSTEMPATH\\Session\\Handlers\\BaseHandler.php"},{"name":"BaseModel.php","path":"SYSTEMPATH\\BaseModel.php"},{"name":"BaseResult.php","path":"SYSTEMPATH\\Database\\BaseResult.php"},{"name":"BaseService.php","path":"SYSTEMPATH\\Config\\BaseService.php"},{"name":"Builder.php","path":"SYSTEMPATH\\Database\\MySQLi\\Builder.php"},{"name":"CacheFactory.php","path":"SYSTEMPATH\\Cache\\CacheFactory.php"},{"name":"CacheInterface.php","path":"SYSTEMPATH\\Cache\\CacheInterface.php"},{"name":"CliRenderer.php","path":"SYSTEMPATH\\ThirdParty\\Kint\\Renderer\\CliRenderer.php"},{"name":"CloneableCookieInterface.php","path":"SYSTEMPATH\\Cookie\\CloneableCookieInterface.php"},{"name":"CodeIgniter.php","path":"SYSTEMPATH\\CodeIgniter.php"},{"name":"Common.php","path":"SYSTEMPATH\\Common.php"},{"name":"Config.php","path":"SYSTEMPATH\\Database\\Config.php"},{"name":"Connection.php","path":"SYSTEMPATH\\Database\\MySQLi\\Connection.php"},{"name":"ConnectionInterface.php","path":"SYSTEMPATH\\Database\\ConnectionInterface.php"},{"name":"ContentSecurityPolicy.php","path":"SYSTEMPATH\\HTTP\\ContentSecurityPolicy.php"},{"name":"Controller.php","path":"SYSTEMPATH\\Controller.php"},{"name":"Cookie.php","path":"SYSTEMPATH\\Cookie\\Cookie.php"},{"name":"CookieInterface.php","path":"SYSTEMPATH\\Cookie\\CookieInterface.php"},{"name":"CookieStore.php","path":"SYSTEMPATH\\Cookie\\CookieStore.php"},{"name":"CreditCardRules.php","path":"SYSTEMPATH\\Validation\\CreditCardRules.php"},{"name":"Database.php","path":"SYSTEMPATH\\Database\\Database.php"},{"name":"Database.php","path":"SYSTEMPATH\\Debug\\Toolbar\\Collectors\\Database.php"},{"name":"DebugToolbar.php","path":"SYSTEMPATH\\Filters\\DebugToolbar.php"},{"name":"DotEnv.php","path":"SYSTEMPATH\\Config\\DotEnv.php"},{"name":"Entity.php","path":"SYSTEMPATH\\Entity.php"},{"name":"Entity.php","path":"SYSTEMPATH\\Entity\\Entity.php"},{"name":"Escaper.php","path":"SYSTEMPATH\\ThirdParty\\Escaper\\Escaper.php"},{"name":"Events.php","path":"SYSTEMPATH\\Debug\\Toolbar\\Collectors\\Events.php"},{"name":"Events.php","path":"SYSTEMPATH\\Events\\Events.php"},{"name":"Exceptions.php","path":"SYSTEMPATH\\Debug\\Exceptions.php"},{"name":"Factories.php","path":"SYSTEMPATH\\Config\\Factories.php"},{"name":"Factory.php","path":"SYSTEMPATH\\Config\\Factory.php"},{"name":"FileHandler.php","path":"SYSTEMPATH\\Cache\\Handlers\\FileHandler.php"},{"name":"FileHandler.php","path":"SYSTEMPATH\\Session\\Handlers\\FileHandler.php"},{"name":"FileLocator.php","path":"SYSTEMPATH\\Autoloader\\FileLocator.php"},{"name":"FileRules.php","path":"SYSTEMPATH\\Validation\\FileRules.php"},{"name":"Files.php","path":"SYSTEMPATH\\Debug\\Toolbar\\Collectors\\Files.php"},{"name":"FilterInterface.php","path":"SYSTEMPATH\\Filters\\FilterInterface.php"},{"name":"Filters.php","path":"SYSTEMPATH\\Filters\\Filters.php"},{"name":"FormatRules.php","path":"SYSTEMPATH\\Validation\\FormatRules.php"},{"name":"Header.php","path":"SYSTEMPATH\\HTTP\\Header.php"},{"name":"IncomingRequest.php","path":"SYSTEMPATH\\HTTP\\IncomingRequest.php"},{"name":"Kint.php","path":"SYSTEMPATH\\ThirdParty\\Kint\\Kint.php"},{"name":"Logger.php","path":"SYSTEMPATH\\Log\\Logger.php"},{"name":"LoggerAwareTrait.php","path":"SYSTEMPATH\\ThirdParty\\PSR\\Log\\LoggerAwareTrait.php"},{"name":"LoggerInterface.php","path":"SYSTEMPATH\\ThirdParty\\PSR\\Log\\LoggerInterface.php"},{"name":"Logs.php","path":"SYSTEMPATH\\Debug\\Toolbar\\Collectors\\Logs.php"},{"name":"Message.php","path":"SYSTEMPATH\\HTTP\\Message.php"},{"name":"MessageInterface.php","path":"SYSTEMPATH\\HTTP\\MessageInterface.php"},{"name":"MessageTrait.php","path":"SYSTEMPATH\\HTTP\\MessageTrait.php"},{"name":"Model.php","path":"SYSTEMPATH\\Model.php"},{"name":"Modules.php","path":"SYSTEMPATH\\Modules\\Modules.php"},{"name":"Query.php","path":"SYSTEMPATH\\Database\\Query.php"},{"name":"QueryInterface.php","path":"SYSTEMPATH\\Database\\QueryInterface.php"},{"name":"RedirectResponse.php","path":"SYSTEMPATH\\HTTP\\RedirectResponse.php"},{"name":"Renderer.php","path":"SYSTEMPATH\\ThirdParty\\Kint\\Renderer\\Renderer.php"},{"name":"RendererInterface.php","path":"SYSTEMPATH\\View\\RendererInterface.php"},{"name":"Request.php","path":"SYSTEMPATH\\HTTP\\Request.php"},{"name":"RequestInterface.php","path":"SYSTEMPATH\\HTTP\\RequestInterface.php"},{"name":"RequestTrait.php","path":"SYSTEMPATH\\HTTP\\RequestTrait.php"},{"name":"Response.php","path":"SYSTEMPATH\\HTTP\\Response.php"},{"name":"ResponseInterface.php","path":"SYSTEMPATH\\HTTP\\ResponseInterface.php"},{"name":"ResponseTrait.php","path":"SYSTEMPATH\\API\\ResponseTrait.php"},{"name":"ResponseTrait.php","path":"SYSTEMPATH\\HTTP\\ResponseTrait.php"},{"name":"Result.php","path":"SYSTEMPATH\\Database\\MySQLi\\Result.php"},{"name":"ResultInterface.php","path":"SYSTEMPATH\\Database\\ResultInterface.php"},{"name":"RichRenderer.php","path":"SYSTEMPATH\\Debug\\Kint\\RichRenderer.php"},{"name":"RichRenderer.php","path":"SYSTEMPATH\\ThirdParty\\Kint\\Renderer\\RichRenderer.php"},{"name":"RouteCollection.php","path":"SYSTEMPATH\\Router\\RouteCollection.php"},{"name":"RouteCollectionInterface.php","path":"SYSTEMPATH\\Router\\RouteCollectionInterface.php"},{"name":"Router.php","path":"SYSTEMPATH\\Router\\Router.php"},{"name":"RouterInterface.php","path":"SYSTEMPATH\\Router\\RouterInterface.php"},{"name":"Routes.php","path":"SYSTEMPATH\\Config\\Routes.php"},{"name":"Routes.php","path":"SYSTEMPATH\\Debug\\Toolbar\\Collectors\\Routes.php"},{"name":"Rules.php","path":"SYSTEMPATH\\Validation\\Rules.php"},{"name":"Services.php","path":"SYSTEMPATH\\Config\\Services.php"},{"name":"Session.php","path":"SYSTEMPATH\\Session\\Session.php"},{"name":"SessionInterface.php","path":"SYSTEMPATH\\Session\\SessionInterface.php"},{"name":"TextRenderer.php","path":"SYSTEMPATH\\ThirdParty\\Kint\\Renderer\\TextRenderer.php"},{"name":"Timer.php","path":"SYSTEMPATH\\Debug\\Timer.php"},{"name":"Timers.php","path":"SYSTEMPATH\\Debug\\Toolbar\\Collectors\\Timers.php"},{"name":"Toolbar.php","path":"SYSTEMPATH\\Debug\\Toolbar.php"},{"name":"URI.php","path":"SYSTEMPATH\\HTTP\\URI.php"},{"name":"UserAgent.php","path":"SYSTEMPATH\\HTTP\\UserAgent.php"},{"name":"Utils.php","path":"SYSTEMPATH\\ThirdParty\\Kint\\Utils.php"},{"name":"Validation.php","path":"SYSTEMPATH\\Validation\\Validation.php"},{"name":"ValidationInterface.php","path":"SYSTEMPATH\\Validation\\ValidationInterface.php"},{"name":"View.php","path":"SYSTEMPATH\\Config\\View.php"},{"name":"View.php","path":"SYSTEMPATH\\View\\View.php"},{"name":"Views.php","path":"SYSTEMPATH\\Debug\\Toolbar\\Collectors\\Views.php"},{"name":"array_helper.php","path":"SYSTEMPATH\\Helpers\\array_helper.php"},{"name":"bootstrap.php","path":"SYSTEMPATH\\bootstrap.php"},{"name":"init.php","path":"SYSTEMPATH\\ThirdParty\\Kint\\init.php"},{"name":"init_helpers.php","path":"SYSTEMPATH\\ThirdParty\\Kint\\init_helpers.php"},{"name":"url_helper.php","path":"SYSTEMPATH\\Helpers\\url_helper.php"}],"userFiles":[{"name":"Airbnb.php","path":"APPPATH\\Config\\Airbnb.php"},{"name":"AnfitrionesModel.php","path":"APPPATH\\Models\\AnfitrionesModel.php"},{"name":"App.php","path":"APPPATH\\Config\\App.php"},{"name":"Autoload.php","path":"APPPATH\\Config\\Autoload.php"},{"name":"BaseController.php","path":"APPPATH\\Controllers\\BaseController.php"},{"name":"Cache.php","path":"APPPATH\\Config\\Cache.php"},{"name":"Common.php","path":"APPPATH\\Common.php"},{"name":"Constants.php","path":"APPPATH\\Config\\Constants.php"},{"name":"ContentSecurityPolicy.php","path":"APPPATH\\Config\\ContentSecurityPolicy.php"},{"name":"Cookie.php","path":"APPPATH\\Config\\Cookie.php"},{"name":"Database.php","path":"APPPATH\\Config\\Database.php"},{"name":"DepartamentosModel.php","path":"APPPATH\\Models\\DepartamentosModel.php"},{"name":"Events.php","path":"APPPATH\\Config\\Events.php"},{"name":"Exceptions.php","path":"APPPATH\\Config\\Exceptions.php"},{"name":"Feature.php","path":"APPPATH\\Config\\Feature.php"},{"name":"Filters.php","path":"APPPATH\\Config\\Filters.php"},{"name":"GuardarPoliticasCancelacionModel.php","path":"APPPATH\\Models\\GuardarPoliticasCancelacionModel.php"},{"name":"GuardarReglasServiciosModel.php","path":"APPPATH\\Models\\GuardarReglasServiciosModel.php"},{"name":"GuardarSaludSeguridadModel.php","path":"APPPATH\\Models\\GuardarSaludSeguridadModel.php"},{"name":"GuardarSubServiciosModel.php","path":"APPPATH\\Models\\GuardarSubServiciosModel.php"},{"name":"HuespedesModel.php","path":"APPPATH\\Models\\HuespedesModel.php"},{"name":"IdiomasModel.php","path":"APPPATH\\Models\\IdiomasModel.php"},{"name":"ImagenesModel.php","path":"APPPATH\\Models\\ImagenesModel.php"},{"name":"Kint.php","path":"APPPATH\\Config\\Kint.php"},{"name":"Logger.php","path":"APPPATH\\Config\\Logger.php"},{"name":"Modules.php","path":"APPPATH\\Config\\Modules.php"},{"name":"MunicipiosModel.php","path":"APPPATH\\Models\\MunicipiosModel.php"},{"name":"PaisesModel.php","path":"APPPATH\\Models\\PaisesModel.php"},{"name":"Paths.php","path":"APPPATH\\Config\\Paths.php"},{"name":"PoliticasCancelacionModel.php","path":"APPPATH\\Models\\PoliticasCancelacionModel.php"},{"name":"ReglasServiciosModel.php","path":"APPPATH\\Models\\ReglasServiciosModel.php"},{"name":"Roles.php","path":"APPPATH\\Filters\\Roles.php"},{"name":"Routes.php","path":"APPPATH\\Config\\Routes.php"},{"name":"SaludSeguridadModel.php","path":"APPPATH\\Models\\SaludSeguridadModel.php"},{"name":"Services.php","path":"APPPATH\\Config\\Services.php"},{"name":"Servicio.php","path":"APPPATH\\Entities\\Servicio.php"},{"name":"ServiciosModel.php","path":"APPPATH\\Models\\ServiciosModel.php"},{"name":"SubServiciosModel.php","path":"APPPATH\\Models\\SubServiciosModel.php"},{"name":"TarifasModel.php","path":"APPPATH\\Models\\TarifasModel.php"},{"name":"TipoHospedajesModel.php","path":"APPPATH\\Models\\TipoHospedajesModel.php"},{"name":"Toolbar.php","path":"APPPATH\\Config\\Toolbar.php"},{"name":"UpdateDelete.php","path":"APPPATH\\Controllers\\Anfitrion\\UpdateDelete.php"},{"name":"UserAgents.php","path":"APPPATH\\Config\\UserAgents.php"},{"name":"Usuario.php","path":"APPPATH\\Entities\\Usuario.php"},{"name":"UsuarioModel.php","path":"APPPATH\\Models\\UsuarioModel.php"},{"name":"Validation.php","path":"APPPATH\\Config\\Validation.php"},{"name":"View.php","path":"APPPATH\\Config\\View.php"},{"name":"development.php","path":"APPPATH\\Config\\Boot\\development.php"},{"name":"index.php","path":"FCPATH\\index.php"}]},"badgeValue":151,"isEmpty":false,"hasTabContent":true,"hasLabel":false,"icon":"data:image\/png;base64,iVBORw0KGgoAAAANSUhEUgAAABgAAAAYCAYAAADgdz34AAAAAXNSR0IArs4c6QAAAARnQU1BAACxjwv8YQUAAAAJcEhZcwAADsMAAA7DAcdvqGQAAAGBSURBVEhL7ZQ9S8NQGIVTBQUncfMfCO4uLgoKbuKQOWg+OkXERRE1IAXrIHbVDrqIDuLiJgj+gro7S3dnpfq88b1FMTE3VZx64HBzzvvZWxKnj15QCcPwCD5HUfSWR+JtzgmtsUcQBEva5IIm9SwSu+95CAWbUuy67qBa32ByZEDpIaZYZSZMjjQuPcQUq8yEyYEb8FSerYeQVGbAFzJkX1PyQWLhgCz0BxTCekC1Wp0hsa6yokzhed4oje6Iz6rlJEkyIKfUEFtITVtQdAibn5rMyaYsMS+a5wTv8qeXMhcU16QZbKgl3hbs+L4\/pnpdc87MElZgq10p5DxGdq8I7xrvUWUKvG3NbSK7ubngYzdJwSsF7TiOh9VOgfcEz1UayNe3JUPM1RWC5GXYgTfc75B4NBmXJnAtTfpABX0iPvEd9ezALwkplCFXcr9styiNOKc1RRZpaPM9tcqBwlWzGY1qPL9wjqRBgF5BH6j8HWh2S7MHlX8PrmbK+k\/8PzjOOzx1D3i1pKTTAAAAAElFTkSuQmCC","hasTimelineData":false,"timelineData":[]},{"title":"Routes","titleSafe":"routes","titleDetails":"","display":{"matchedRoute":[{"directory":"","controller":"\\App\\Controllers\\Anfitrion\\UpdateDelete","method":"ActualizarServicio","paramCount":0,"truePCount":0,"params":[]}],"routes":[{"method":"GET","route":"\/","handler":"\\App\\Controllers\\Home\\Home::index"},{"method":"GET","route":"auth\/registro","handler":"\\App\\Controllers\\Auth\\Vistas::index"},{"method":"GET","route":"auth\/registro-anfitrion","handler":"\\App\\Controllers\\Auth\\Vistas::registrarAnfitrion"},{"method":"GET","route":"auth\/login","handler":"\\App\\Controllers\\Auth\\Vistas::login"},{"method":"GET","route":"usuario\/registrar","handler":"\\App\\Controllers\\Usuario\\Vistas::hazteAnfitrion"},{"method":"GET","route":"usuario\/perfil","handler":"\\App\\Controllers\\Usuario\\Vistas::perfil"},{"method":"GET","route":"usuario\/inicio","handler":"\\App\\Controllers\\Usuario\\Vistas::index"},{"method":"GET","route":"usuario\/alojamiento","handler":"\\App\\Controllers\\Usuario\\Vistas::alojamiento"},{"method":"GET","route":"usuario\/cerrar","handler":"\\App\\Controllers\\Usuario\\Registro::cerrar"},{"method":"GET","route":"anfitrion\/inicio","handler":"\\App\\Controllers\\Anfitrion\\Vistas::index"},{"method":"GET","route":"anfitrion\/perfil","handler":"\\App\\Controllers\\Anfitrion\\Vistas::perfil"},{"method":"GET","route":"anfitrion\/publicar","handler":"\\App\\Controllers\\Anfitrion\\Vistas::publicar"},{"method":"GET","route":"anfitrion\/buscar","handler":"\\App\\Controllers\\Anfitrion\\Vistas::buscar"},{"method":"GET","route":"anfitrion\/cerrar","handler":"\\App\\Controllers\\Anfitrion\\Registro::cerrar"},{"method":"GET","route":"anfitrion\/servicio","handler":"\\App\\Controllers\\Anfitrion\\Vistas::verServicio"},{"method":"GET","route":"anfitrion\/de-baja","handler":"\\App\\Controllers\\Anfitrion\\UpdateDelete::darBajaServicio"},{"method":"GET","route":"anfitrion\/de-alta","handler":"\\App\\Controllers\\Anfitrion\\UpdateDelete::darAltaServicio"},{"method":"GET","route":"anfitrion\/actualizar","handler":"\\App\\Controllers\\Anfitrion\\Vistas::actualizarServicio"},{"method":"GET","route":"anfitrion\/actualizar-perfil","handler":"\\App\\Controllers\\Anfitrion\\Vistas::actualizarPerfil"},{"method":"GET","route":"admin\/inicio","handler":"\\App\\Controllers\\Admin\\Admin::index"},{"method":"GET","route":"admin\/buscar","handler":"\\App\\Controllers\\Admin\\Admin::buscar"},{"method":"GET","route":"admin\/cerrar","handler":"\\App\\Controllers\\Admin\\Admin::cerrar"},{"method":"POST","route":"auth\/registrar","handler":"\\App\\Controllers\\Auth\\Registro::registrar"},{"method":"POST","route":"auth\/registrar-anfitrion","handler":"\\App\\Controllers\\Auth\\Registro::registrarAnfitrion"},{"method":"POST","route":"auth\/checklogin","handler":"\\App\\Controllers\\Auth\\Login::signin"},{"method":"POST","route":"usuario\/registrarAnfitrion","handler":"\\App\\Controllers\\Usuario\\Registro::registrarAnfitrion"},{"method":"POST","route":"anfitrion\/RegistrarPublicacion","handler":"\\App\\Controllers\\Anfitrion\\Registro::RegistrarPublicacion"},{"method":"POST","route":"anfitrion\/ActualizarServicio","handler":"\\App\\Controllers\\Anfitrion\\UpdateDelete::ActualizarServicio"},{"method":"POST","route":"anfitrion\/ActualizarPerfil","handler":"\\App\\Controllers\\Anfitrion\\UpdateDelete::ActualizarPerfil"},{"method":"CLI","route":"migrations\/([^\/]+)\/([^\/]+)","handler":"\\CodeIgniter\\Commands\\MigrationsCommand::$1\/$2"},{"method":"CLI","route":"migrations\/([^\/]+)","handler":"\\CodeIgniter\\Commands\\MigrationsCommand::$1"},{"method":"CLI","route":"migrations","handler":"\\CodeIgniter\\Commands\\MigrationsCommand::index"},{"method":"CLI","route":"ci(.*)","handler":"\\CodeIgniter\\CLI\\CommandRunner::index\/$1"}]},"badgeValue":9,"isEmpty":false,"hasTabContent":true,"hasLabel":false,"icon":"data:image\/png;base64,iVBORw0KGgoAAAANSUhEUgAAABgAAAAYCAYAAADgdz34AAAAAXNSR0IArs4c6QAAAARnQU1BAACxjwv8YQUAAAAJcEhZcwAADsMAAA7DAcdvqGQAAAFDSURBVEhL7ZRNSsNQFIUjVXSiOFEcuQIHDpzpxC0IGYeE\/BEInbWlCHEDLsSiuANdhKDjgm6ggtSJ+l25ldrmmTwIgtgDh\/t37r1J+16cX0dRFMtpmu5pWAkrvYjjOB7AETzStBFW+inxu3KUJMmhludQpoflS1zXban4LYqiO224h6VLTHr8Z+z8EpIHFF9gG78nDVmW7UgTHKjsCyY98QP+pcq+g8Ku2s8G8X3f3\/I8b038WZTp+bO38zxfFd+I6YY6sNUvFlSDk9CRhiAI1jX1I9Cfw7GG1UB8LAuwbU0ZwQnbRDeEN5qqBxZMLtE1ti9LtbREnMIuOXnyIf5rGIb7Wq8HmlZgwYBH7ORTcKH5E4mpjeGt9fBZcHE2GCQ3Vt7oTNPNg+FXLHnSsHkw\/FR+Gg2bB8Ptzrst\/v6C\/wrH+QB+duli6MYJdQAAAABJRU5ErkJggg==","hasTimelineData":false,"timelineData":[]},{"title":"Events","titleSafe":"events","titleDetails":"","display":{"events":{"pre_system":{"event":"pre_system","duration":"29.39","count":1},"dbquery":{"event":"dbquery","duration":"1.37","count":23}}},"badgeValue":24,"isEmpty":false,"hasTabContent":true,"hasLabel":false,"icon":"data:image\/png;base64,iVBORw0KGgoAAAANSUhEUgAAABgAAAAYCAYAAADgdz34AAAAAXNSR0IArs4c6QAAAARnQU1BAACxjwv8YQUAAAAJcEhZcwAADsMAAA7DAcdvqGQAAAEASURBVEhL7ZXNDcIwDIVTsRBH1uDQDdquUA6IM1xgCA6MwJUN2hk6AQzAz0vl0ETUxC5VT3zSU5w81\/mRMGZysixbFEVR0jSKNt8geQU9aRpFmp\/keX6AbjZ5oB74vsaN5lSzA4tLSjpBFxsjeSuRy4d2mDdQTWU7YLbXTNN05mKyovj5KL6B7q3hoy3KwdZxBlT+Ipz+jPHrBqOIynZgcZonoukb\/0ckiTHqNvDXtXEAaygRbaB9FvUTjRUHsIYS0QaSp+Dw6wT4hiTmYHOcYZsdLQ2CbXa4ftuuYR4x9vYZgdb4vsFYUdmABMYeukK9\/SUme3KMFQ77+Yfzh8eYF8+orDuDWU5LAAAAAElFTkSuQmCC","hasTimelineData":false,"timelineData":[]}],"vars":{"varData":{"View Data":[]},"session":{"__ci_last_regenerate":"<pre>1666712600<\/pre>","_ci_previous_url":"http:\/\/proyect_airbnb.test\/anfitrion\/actualizar?id=%242y%2410%24vO7KArkz3uHuRMOPR0S6wOMpjSD.MVPqhn4LpPfn5VuB9HEXc%2FjU2","idUsuario":"1","idAnfitrion":"1","username":"Bryan Amaya","idRol":"3","rol":"Anfitrion","email":"brayanantonio816@gmail.com","rol2":"Anfitrion","is_logged":"<pre>1<\/pre>","msg":"<pre>Array\n(\n    [type] =&gt; success\n    [body] =&gt; Publicacion actualizada con exito!\n)\n<\/pre>","__ci_vars":"<pre>Array\n(\n    [msg] =&gt; new\n)\n<\/pre>"},"get":{"id":"$2y$10$DVsfKseaqIlj6nMuoFRUNulGFsgOE35OPDPXdh915Vk5\/0B8zIvDq"},"post":{"nombre":"Servicio 1","idTipoHospedaje":"1","descripcion":"Caba\u00f1a con un clima fresco con temperaturas bajas no encontrada en el pais.","precio":"100","direccion":"Av. 3 calle poniente","descuento":"10","adultos":"2","menores":"3","bebes":"1","mascotas":"1","idSubServicio":"<pre>Array\n(\n    [0] =&gt; 1\n    [1] =&gt; 2\n)\n<\/pre>","idSaludSeguridad":"<pre>Array\n(\n    [0] =&gt; 1\n    [1] =&gt; 2\n)\n<\/pre>","idReglaServicio":"<pre>Array\n(\n    [0] =&gt; 1\n    [1] =&gt; 3\n)\n<\/pre>","idPoliticaCancelacion":"<pre>Array\n(\n    [0] =&gt; 1\n)\n<\/pre>"},"headers":{"Content-Type":"multipart\/form-data; boundary=---------------------------69110247438242655511160544","Host":"proyect_airbnb.test","User-Agent":"Mozilla\/5.0 (Windows NT 10.0; Win64; x64; rv:106.0) Gecko\/20100101 Firefox\/106.0","Accept":"text\/html,application\/xhtml+xml,application\/xml;q=0.9,image\/avif,image\/webp,*\/*;q=0.8","Accept-Language":"es-ES,es;q=0.8,en-US;q=0.5,en;q=0.3","Accept-Encoding":"gzip, deflate","Origin":"http:\/\/proyect_airbnb.test","Connection":"keep-alive","Referer":"http:\/\/proyect_airbnb.test\/anfitrion\/actualizar?id=$2y$10$vO7KArkz3uHuRMOPR0S6wOMpjSD.MVPqhn4LpPfn5VuB9HEXc\/jU2","Cookie":"ci_session=381mloancrcqcffv7jfdggg4b5gjrmv1","Upgrade-Insecure-Requests":"1"},"cookies":{"ci_session":"381mloancrcqcffv7jfdggg4b5gjrmv1"},"request":"HTTP\/1.1","response":{"statusCode":303,"reason":"See Other","contentType":"text\/html; charset=UTF-8"}},"config":{"ciVersion":"4.1.8","phpVersion":"8.1.7","phpSAPI":"apache2handler","environment":"development","baseURL":"http:\/\/proyect_airbnb.test\/","timezone":"America\/Managua","locale":"es","cspEnabled":false}}